{"content": "# Krzy\u017c Komandorski z Gwiazd\u0105 Orderu Zas\u0142ugi Rzeczypospolitej Polskiej \u2013 Historia AGH\n\nURL: https://historia.agh.edu.pl/wiki/Krzy%C5%BC_Komandorski_z_Gwiazd%C4%85_Orderu_Zas%C5%82ugi_Rzeczypospolitej_Polskiej\nCrawled: 2025-03-19 22:27:21\n\nKrzy\u017c Komandorski z Gwiazd\u0105 Orderu Zas\u0142ugi Rzeczypospolitej Polskiej\n\nZ Historia AGH\n\nOdznaczeni:\n\nHo Chi Hung\n, \nNguyen Khoi Pham\n\n\u0179r\u00f3d\u0142o: \u201e\nhttp://historia.agh.edu.pl/mediawiki/index.php?title=Krzy\u017c_Komandorski_z_Gwiazd\u0105_Orderu_Zas\u0142ugi_Rzeczypospolitej_Polskiej&oldid=35545\n\u201d\n\nKategoria\n: \nOdznaczenie", "metadata": {"url": "https://historia.agh.edu.pl/wiki/Krzy%C5%BC_Komandorski_z_Gwiazd%C4%85_Orderu_Zas%C5%82ugi_Rzeczypospolitej_Polskiej", "title": "Krzy\u017c Komandorski z Gwiazd\u0105 Orderu Zas\u0142ugi Rzeczypospolitej Polskiej \u2013 Historia AGH", "depth": 3, "duplicate": false, "content_hash": "655c39a8f008abf90172e6a1bc518b2a", "word_count": 26, "headings": [{"level": 1, "text": "Krzy\u017c Komandorski z Gwiazd\u0105 Orderu Zas\u0142ugi Rzeczypospolitej Polskiej"}]}}