{"content": "#  Kosmos dla Spo\u0142ecze\u0144stwa -- Centrum Technologii Kosmicznych \n\nURL: https://www.ctk.agh.edu.pl/grupy-badawcze/kosmos-dla-spoleczenstwa\nCrawled: 2025-03-19 21:40:20\n\nPrzejd\u017a do tre\u015bci\n\nPrzejd\u017a do stopki\n\n Kosmos dla Spo\u0142ecze\u0144stwa \n\nGrupa badawcza Space Society Lab koncentruje si\u0119 na promowaniu inkluzywno\u015bci i interdyscyplinarno\u015bci w dziedzinie technologii kosmicznych, zach\u0119caj\u0105c do udzia\u0142u zar\u00f3wno kobiety, m\u0119\u017cczyzn, osoby z mniejszych miejscowo\u015bci, jak i osoby ze specjalnymi potrzebami. Naszym celem jest budowanie bran\u017cy kosmicznej otwartej dla wszystkich, w kt\u00f3rej ka\u017cdy mo\u017ce mie\u0107 sw\u00f3j wk\u0142ad. W ramach naszych dzia\u0142a\u0144 wspieramy r\u00f3wnie\u017c zr\u00f3wnowa\u017cony rozw\u00f3j sektora kosmicznego.\n\nDzia\u0142alno\u015b\u0107 Space Society Lab opiera si\u0119 na:\n\nPromowaniu mobilno\u015bci studenckiej i wymiany kulturowej\n, m.in. poprzez vlogi z podr\u00f3\u017cy oraz organizacj\u0119 mi\u0119dzynarodowych konferencji studenckich, co przyczynia si\u0119 do lepszego zrozumienia r\u00f3\u017cnorodnych perspektyw.\n\nOrganizacji wydarze\u0144 online i stacjonarnych\u00a0skierowanych do szk\u00f3\u0142\n i spo\u0142eczno\u015bci lokalnych, realizowanych pod has\u0142em \u201eKosmos dla wszystkich\u201d, aby inspirowa\u0107 m\u0142ode pokolenia i poszerza\u0107 dost\u0119p do wiedzy o przestrzeni kosmicznej.\n\nPodkre\u015blaniu znaczenia r\u00f3\u017cnorodno\u015bci\u00a0w projektach kosmicznych\n, pokazuj\u0105c, jak r\u00f3\u017cnorodne zespo\u0142y mog\u0105 przyczyni\u0107 si\u0119 do sukces\u00f3w technologicznych i innowacji w tej bran\u017cy.\n\nBadaniach dotycz\u0105cych spo\u0142ecznego postrzegania kosmosu\n, kt\u00f3re pozwalaj\u0105 zrozumie\u0107, jak eksploracja kosmosu wp\u0142ywa na ludzkie aspiracje, warto\u015bci i wyobra\u017cenia o przysz\u0142o\u015bci.\n\nWzmacnianiu poczucia w\u0142asnej warto\u015bci i pewno\u015bci siebie\u00a0poprzez programy rozwojowe\n, kt\u00f3re pomagaj\u0105 jednostkom uwierzy\u0107 w swoje mo\u017cliwo\u015bci w bran\u017cy technologii kosmicznych.\n\nPrezentowaniu inspiruj\u0105cych postaci (role models)\n, kt\u00f3re pokazuj\u0105, \u017ce kariera w kosmosie jest osi\u0105galna dla ka\u017cdego, bez wzgl\u0119du na pochodzenie, p\u0142e\u0107 czy warunki fizyczne.\n\nSpace Society Lab dzia\u0142a z przekonaniem, \u017ce dost\u0119p do przestrzeni kosmicznej oraz technologii powinien by\u0107 dost\u0119pny dla wszystkich, tworz\u0105c bran\u017c\u0119 przyjazn\u0105, r\u00f3\u017cnorodn\u0105 i otwart\u0105 na nowe perspektywy.\n\nStopka\n\nBack", "metadata": {"url": "https://www.ctk.agh.edu.pl/grupy-badawcze/kosmos-dla-spoleczenstwa", "title": " Kosmos dla Spo\u0142ecze\u0144stwa -- Centrum Technologii Kosmicznych ", "depth": 3, "duplicate": false, "content_hash": "d88c9b293aff1156a732d39d45e4a974", "word_count": 246, "headings": [{"level": 1, "text": "Kosmos dla Spo\u0142ecze\u0144stwa"}, {"level": 2, "text": "Stopka"}]}}