{"content": "#  Senate Committee for Statutes and Regulations -- AGH UST \n\nURL: https://agh.edu.pl/en/o-agh/wladze/senat/tytul-domyslny-1\nCrawled: 2025-03-19 21:18:58\n\nSkip to content \u2193\n\n Senate Committee for Statutes and Regulations \n\n\u00a0 \u00a0 Professor Tomasz Barszcz \u2013 Chairperson, WIMiR\n\n\u00a0\u00a0\u00a0 Associate Professor Arkadiusz Kustra, WILiGZ\n\n\u00a0\u00a0\u00a0 Associate Professor Piotr Ba\u0142a, WIMiIP\n\n\u00a0\u00a0\u00a0 Professor Marcin Szpyrka, WEAIiIB\n\n\u00a0\u00a0\u00a0 Associate Professor Krzysztof Wincza, WIEiT\n\n\u00a0\u00a0\u00a0 Associate Professor Jaros\u0142aw Konieczny, WIMiR\n\n\u00a0\u00a0\u00a0 Associate Professor Ewa Kmiecik, WGGiO\u015a\n\n\u00a0\u00a0\u00a0 Associate Professor Edward Preweda, WGGiI\u015a\n\n\u00a0\u00a0\u00a0 Professor El\u017cbieta Pamu\u0142a, WIMiC\n\n\u00a0\u00a0\u00a0 Dr Iwona Grelowska, WIMiC\n\n\u00a0\u00a0\u00a0 Dr Karolina Kaczmarska, WO\n\n\u00a0\u00a0\u00a0 Associate Professor Andrzej Mamala, WMN\n\n\u00a0\u00a0\u00a0 Professor Jerzy Stopa, WWNiG\n\n\u00a0\u00a0\u00a0 Associate Professor Joanna Kulczycka, WZ\n\n\u00a0\u00a0\u00a0 Professor Konrad \u015awierczek, WEiP\n\n\u00a0\u00a0\u00a0 Professor Piotr Bo\u017cek, WFiIS\n\n\u00a0\u00a0\u00a0 Associate Professor Pawe\u0142 Przyby\u0142owicz, WMS\n\n\u00a0\u00a0\u00a0 Associate Professor Barbara G\u0105ciarz, WH\n\n\u00a0\u00a0\u00a0 Professor Marek Przybylski, ACMiN\n\n\u00a0\u00a0\u00a0 Krzysztof Obertyn, student representative\n\n\u00a0\u00a0\u00a0 Mateusz Gala, MSc Eng., doctoral student representative\n\nStopka\n\nWelcome to AGH University\n\nAGH University Strategy\n\nExcellence Initiative \u2013 Research University\n\nUNIVERSEH\n\nResearch offer\n\nBusiness offer\n\nCentre for International Affairs\n\nWelcome Point\n\nFaculties\n\nMain Library\n\nAGH University Student Campus\n\nCareers Centre\n\nContact\n\nMap of the AGH University Campus\n\nAGH University e-Shop\n\nEmployee Search\n\nHRS4R\n\nEquality statement\n\nPersonal data protection\n\nMake a donation\n\nBack", "metadata": {"url": "https://agh.edu.pl/en/o-agh/wladze/senat/tytul-domyslny-1", "title": " Senate Committee for Statutes and Regulations -- AGH UST ", "depth": 3, "duplicate": false, "content_hash": "3e4d9e7368b3e0b37e3eaf86f7f47249", "word_count": 164, "headings": [{"level": 1, "text": "Senate Committee for Statutes and Regulations"}, {"level": 2, "text": "Stopka"}]}}