{"content": "# Nauka o materia\u0142ach \u2013 Historia AGH\n\nURL: https://historia.agh.edu.pl/wiki/Nauka_o_materia%C5%82ach\nCrawled: 2025-03-19 22:10:10\n\nNauka o materia\u0142ach\n\nZ Historia AGH\n\nReprezentanci:\n\nJerzy W\u0142odzimierz Bia\u0142osk\u00f3rski\n, \nAleksander Gil\n, \nRoman Kazimierz Pampuch\n, \nJan W\u0142adys\u0142aw Piekarczyk\n, \nWaldemar Pyda\n, \nLeszek Stanis\u0142aw Stoch\n, \nKrzysztof Tadeusz Wierzbanowski\n\n\u0179r\u00f3d\u0142o: \u201e\nhttp://historia.agh.edu.pl/mediawiki/index.php?title=Nauka_o_materia\u0142ach&oldid=34110\n\u201d\n\nKategoria\n: \nDyscyplina/Specjalno\u015bci", "metadata": {"url": "https://historia.agh.edu.pl/wiki/Nauka_o_materia%C5%82ach", "title": "Nauka o materia\u0142ach \u2013 Historia AGH", "depth": 3, "duplicate": false, "content_hash": "b66a43228a15b0d13a50eff1060c57d0", "word_count": 39, "headings": [{"level": 1, "text": "Nauka o materia\u0142ach"}]}}