{"metadata": {"url": "https://rekrutacja.agh.edu.pl/warunki-rekrutacji/", "title": "Warunki Rekrutacji \u2013 Strona Centrum Rekrutacji", "depth": 1, "duplicate": false, "content_hash": "537409867edaa32b97e108a2e0fcb84b", "word_count": 6942, "headings": [{"level": 1, "text": "Strona Centrum Rekrutacji - Warunki Rekrutacji"}, {"level": 1, "text": "WARUNKI I TRYB REKRUTACJI"}, {"level": 2, "text": "STUDIA I STOPNIA"}, {"level": 2, "text": "STUDIA II STOPNIA"}, {"level": 4, "text": "WR = M + 3 \u00b7G1+G2"}, {"level": 4, "text": ""}, {"level": 4, "text": "WR = wE\u00b7 E + wS\u00b7 S"}, {"level": 4, "text": "wE+ wS= 10"}, {"level": 3, "text": "ZASADY WYLICZANIA WSKA\u0179NIKA REKRUTACJI"}, {"level": 4, "text": "1) dla kandydat\u00f3w kwalifikowanych na podstawie wynik\u00f3w egzaminu maturalnego w skali 0-100% punkt\u00f3w, wska\u017anik rekrutacji obliczony jest wed\u0142ug wzoru (1)"}, {"level": 4, "text": "WR = M + 3 \u00b7G1+G2"}, {"level": 4, "text": ""}, {"level": 4, "text": "G1,2= NP"}, {"level": 4, "text": "$$\\mathsf{G_{1,2}} = \\left \\{ \\begin{array}{ll} \\mathsf{N_R} &\\textsf{dla} & \\mathsf{N_R}\\lt \\mathsf{30} \\\\ \\mathsf{N_R+2(N_R-30)} & \\mathsf{dla} & \\mathsf{30} \\leq \\mathsf{N_R} \\leq \\mathsf{80} \\\\ \\mathsf{N_R+100} & \\mathsf{dla} & \\mathsf{N_R} \\gt \\mathsf{80} \\end{array} \\right. $$"}, {"level": 4, "text": "$$ \\mathsf{G_{1,2}} = \\left \\{ \\begin{array}{ll} \\mathsf{2*N_D} & \\mathsf{dla} & \\mathsf{N_D}\\lt \\mathsf{30} \\\\ \\mathsf{N_D+100} & \\mathsf{dla} & \\mathsf{30} \\leq \\mathsf{N_D} \\leq \\mathsf{50} \\\\ \\mathsf{200} & \\mathsf{dla} & \\mathsf{N_D} \\gt \\mathsf{50} \\end{array} \\right. $$"}, {"level": 4, "text": "2) dla kandydat\u00f3w kwalifikowanych na podstawie wynik\u00f3w egzaminu dojrza\u0142o\u015bci w skali ocen 1-6 lub 2-5 wska\u017anik rekrutacji obliczony jest zgodnie ze wzorem (1)"}, {"level": 4, "text": "WR = M + 3 \u00b7G1+G2"}, {"level": 4, "text": ""}, {"level": 4, "text": "N = 30 + 70 (N0-Nmin)/(Nmax-Nmin)"}, {"level": 4, "text": "3) dla kandydat\u00f3w kwalifikowanych na podstawie wynik\u00f3w egzamin\u00f3w maturalnych i egzamin\u00f3w potwierdzaj\u0105cych kwalifikacje w zawodzie, wska\u017anik rekrutacji obliczany jest wed\u0142ug wzoru (1)"}, {"level": 4, "text": "WR = M + 3 \u00b7G1+G2"}, {"level": 4, "text": ""}, {"level": 4, "text": "W = 0,3 x Wp+ 0,7 x Wpr"}, {"level": 4, "text": "4) dla kandydat\u00f3w kwalifikowanych na podstawie wynik\u00f3w egzamin\u00f3w maturalnych i egzaminu/egzamin\u00f3w zawodowych, wska\u017anik rekrutacji obliczany jest wed\u0142ug wzoru (1)"}, {"level": 4, "text": "WR = M + 3 \u00b7G1+G2"}, {"level": 4, "text": ""}, {"level": 4, "text": "5) dla kandydat\u00f3w kwalifikowanych na podstawie wynik\u00f3w egzaminu zagranicznego lub wynik\u00f3w kszta\u0142cenia potwierdzonych \u015bwiadectwem, dyplomem lub innym dokumentem, o kt\u00f3rym mowa w art. 69 ust. 2 pkt 4-7 ustawy z dnia 20 lipca 2018 r. Prawo o szkolnictwie wy\u017cszym i nauce z wy\u0142\u0105czeniem matury mi\u0119dzynarodowej (IB) i matury europejskiej (EB) wska\u017anik rekrutacji obliczony jest wed\u0142ug wzoru (1)"}, {"level": 4, "text": "WR = M + 3 \u00b7G1+G2"}, {"level": 4, "text": ""}, {"level": 5, "text": "G1,2= NP"}, {"level": 4, "text": "$$\\mathsf{G_{1,2}} = \\left \\{ \\begin{array}{ll} \\mathsf{N_R} &\\textsf{dla} & \\mathsf{N_R}\\lt \\mathsf{30} \\\\ \\mathsf{N_R+2(N_R-30)} & \\mathsf{dla} & \\mathsf{30} \\leq \\mathsf{N_R} \\leq \\mathsf{80} \\\\ \\mathsf{N_R+100} & \\mathsf{dla} & \\mathsf{N_R} \\gt \\mathsf{80} \\end{array} \\right. $$"}, {"level": 5, "text": ""}, {"level": 5, "text": "N = 30 + 70 (N0-Nmin)/(Nmax-Nmin)"}, {"level": 4, "text": "6) dla kandydat\u00f3w kwalifikowanych na podstawie wynik\u00f3w egzaminu maturalnego zdawanego wed\u0142ug zasad matury mi\u0119dzynarodowej IB (International Baccalaureate) wska\u017anik rekrutacji obliczony jest wed\u0142ug wzoru (1)"}, {"level": 4, "text": "WR = M + 3 \u00b7G1+G2"}, {"level": 4, "text": ""}, {"level": 5, "text": "G1,2= NP"}, {"level": 4, "text": "$$\\mathsf{G_{1,2}} = \\left \\{ \\begin{array}{ll} \\mathsf{N_R} &\\textsf{dla} & \\mathsf{N_R}\\lt \\mathsf{30} \\\\ \\mathsf{N_R+2(N_R-30)} & \\mathsf{dla} & \\mathsf{30} \\leq \\mathsf{N_R} \\leq \\mathsf{80} \\\\ \\mathsf{N_R+100} & \\mathsf{dla} & \\mathsf{N_R} \\gt \\mathsf{80} \\end{array} \\right. $$"}, {"level": 5, "text": "N = 30 + 70 (N0-Nmin)/(Nmax-Nmin)"}, {"level": 4, "text": "6) dlakandydat\u00f3wkwalifikowanych na podstawie wynik\u00f3w egzaminu maturalnego zdawanego wed\u0142ug zasad matury europejskiej EB (European Baccalaureate) wska\u017anik rekrutacji obliczony jest wed\u0142ug wzoru (1)"}, {"level": 4, "text": "WR = M + 3 \u00b7G1+G2"}, {"level": 4, "text": ""}, {"level": 4, "text": "G1,2= NP"}, {"level": 4, "text": "$$\\mathsf{G_{1,2}} = \\left \\{ \\begin{array}{ll} \\mathsf{N_R} &\\textsf{dla} & \\mathsf{N_R}\\lt \\mathsf{30} \\\\ \\mathsf{N_R+2(N_R-30)} & \\mathsf{dla} & \\mathsf{30} \\leq \\mathsf{N_R} \\leq \\mathsf{80} \\\\ \\mathsf{N_R+100} & \\mathsf{dla} & \\mathsf{N_R} \\gt \\mathsf{80} \\end{array} \\right. $$"}, {"level": 4, "text": "N = 30 + 70 (N0-Nmin)/(Nmax-Nmin)"}, {"level": 4, "text": "1) dla kandydat\u00f3w kwalifikowanych na podstawie wynik\u00f3w egzaminu maturalnego w skali 0-100% punkt\u00f3w, wska\u017anik rekrutacji obliczony jest wed\u0142ug wzoru (1)"}, {"level": 4, "text": "WR = M + 3 \u00b7G1+G2"}, {"level": 4, "text": ""}, {"level": 4, "text": "G1,2= NP"}, {"level": 4, "text": "$$\\mathsf{G_{1,2}} = \\left \\{ \\begin{array}{ll} \\mathsf{N_R} &\\textsf{dla} & \\mathsf{N_R}\\lt \\mathsf{30} \\\\ \\mathsf{N_R+2(N_R-30)} & \\mathsf{dla} & \\mathsf{30} \\leq \\mathsf{N_R} \\leq \\mathsf{80} \\\\ \\mathsf{N_R+100} & \\mathsf{dla} & \\mathsf{N_R} \\gt \\mathsf{80} \\end{array} \\right. $$"}, {"level": 4, "text": "$$ \\mathsf{G_{1,2}} = \\left \\{ \\begin{array}{ll} \\mathsf{2*N_D} & \\mathsf{dla} & \\mathsf{N_D}\\lt \\mathsf{30} \\\\ \\mathsf{N_D+100} & \\mathsf{dla} & \\mathsf{30} \\leq \\mathsf{N_D} \\leq \\mathsf{50} \\\\ \\mathsf{200} & \\mathsf{dla} & \\mathsf{N_D} \\gt \\mathsf{50} \\end{array} \\right. $$"}, {"level": 4, "text": "2) dla kandydat\u00f3w kwalifikowanych na podstawie wynik\u00f3w egzaminu dojrza\u0142o\u015bci w skali ocen 1-6 lub 2-5 wska\u017anik rekrutacji obliczony jest zgodnie ze wzorem (1)"}, {"level": 4, "text": "WR = M + 3 \u00b7G1+G2"}, {"level": 4, "text": ""}, {"level": 4, "text": "N = 30 + 70 (N0-Nmin)/(Nmax-Nmin)"}, {"level": 4, "text": "3) dla kandydat\u00f3w kwalifikowanych na podstawie wynik\u00f3w egzamin\u00f3w maturalnych i egzamin\u00f3w potwierdzaj\u0105cych kwalifikacje w zawodzie, wska\u017anik rekrutacji obliczany jest wed\u0142ug wzoru (1)"}, {"level": 4, "text": "WR = M + 3 \u00b7G1+G2"}, {"level": 4, "text": ""}, {"level": 4, "text": "W = 0,3 x Wp+ 0,7 x Wpr"}, {"level": 4, "text": "4) dla kandydat\u00f3w kwalifikowanych na podstawie wynik\u00f3w egzamin\u00f3w maturalnych i egzaminu/egzamin\u00f3w zawodowych, wska\u017anik rekrutacji obliczany jest wed\u0142ug wzoru (1)"}, {"level": 4, "text": "WR = M + 3 \u00b7G1+G2"}, {"level": 4, "text": ""}, {"level": 4, "text": "5) dla kandydat\u00f3w kwalifikowanych na podstawie wynik\u00f3w egzaminu zagranicznego lub wynik\u00f3w kszta\u0142cenia potwierdzonych \u015bwiadectwem, dyplomem lub innym dokumentem, o kt\u00f3rym mowa w art. 69 ust. 2 pkt 4-7 ustawy z dnia 20 lipca 2018 r. Prawo o szkolnictwie wy\u017cszym i nauce z wy\u0142\u0105czeniem matury mi\u0119dzynarodowej (IB) i matury europejskiej (EB) wska\u017anik rekrutacji obliczony jest wed\u0142ug wzoru (1)"}, {"level": 4, "text": "WR = M + 3 \u00b7G1+G2"}, {"level": 4, "text": ""}, {"level": 5, "text": "G1,2= NP"}, {"level": 4, "text": "$$\\mathsf{G_{1,2}} = \\left \\{ \\begin{array}{ll} \\mathsf{N_R} &\\textsf{dla} & \\mathsf{N_R}\\lt \\mathsf{30} \\\\ \\mathsf{N_R+2(N_R-30)} & \\mathsf{dla} & \\mathsf{30} \\leq \\mathsf{N_R} \\leq \\mathsf{80} \\\\ \\mathsf{N_R+100} & \\mathsf{dla} & \\mathsf{N_R} \\gt \\mathsf{80} \\end{array} \\right. $$"}, {"level": 5, "text": ""}, {"level": 5, "text": "N = 30 + 70 (N0-Nmin)/(Nmax-Nmin)"}, {"level": 4, "text": "6) dla kandydat\u00f3w kwalifikowanych na podstawie wynik\u00f3w egzaminu maturalnego zdawanego wed\u0142ug zasad matury mi\u0119dzynarodowej IB (International Baccalaureate) wska\u017anik rekrutacji obliczony jest wed\u0142ug wzoru (1)"}, {"level": 4, "text": "WR = M + 3 \u00b7G1+G2"}, {"level": 4, "text": ""}, {"level": 5, "text": "G1,2= NP"}, {"level": 4, "text": "$$\\mathsf{G_{1,2}} = \\left \\{ \\begin{array}{ll} \\mathsf{N_R} &\\textsf{dla} & \\mathsf{N_R}\\lt \\mathsf{30} \\\\ \\mathsf{N_R+2(N_R-30)} & \\mathsf{dla} & \\mathsf{30} \\leq \\mathsf{N_R} \\leq \\mathsf{80} \\\\ \\mathsf{N_R+100} & \\mathsf{dla} & \\mathsf{N_R} \\gt \\mathsf{80} \\end{array} \\right. $$"}, {"level": 5, "text": "N = 30 + 70 (N0-Nmin)/(Nmax-Nmin)"}, {"level": 4, "text": "6) dlakandydat\u00f3wkwalifikowanych na podstawie wynik\u00f3w egzaminu maturalnego zdawanego wed\u0142ug zasad matury europejskiej EB (European Baccalaureate) wska\u017anik rekrutacji obliczony jest wed\u0142ug wzoru (1)"}, {"level": 4, "text": "WR = M + 3 \u00b7G1+G2"}, {"level": 4, "text": ""}, {"level": 4, "text": "G1,2= NP"}, {"level": 4, "text": "$$\\mathsf{G_{1,2}} = \\left \\{ \\begin{array}{ll} \\mathsf{N_R} &\\textsf{dla} & \\mathsf{N_R}\\lt \\mathsf{30} \\\\ \\mathsf{N_R+2(N_R-30)} & \\mathsf{dla} & \\mathsf{30} \\leq \\mathsf{N_R} \\leq \\mathsf{80} \\\\ \\mathsf{N_R+100} & \\mathsf{dla} & \\mathsf{N_R} \\gt \\mathsf{80} \\end{array} \\right. $$"}, {"level": 4, "text": "N = 30 + 70 (N0-Nmin)/(Nmax-Nmin)"}, {"level": 3, "text": "O CO NAJCZ\u0118\u015aCIEJ PYTACIE"}, {"level": 2, "text": "STUDIA I STOPNIA"}, {"level": 2, "text": "STUDIA II STOPNIA"}, {"level": 4, "text": "FAQ"}, {"level": 4, "text": "Czemu nie mog\u0119 si\u0119 zalogowa\u0107 na konto z poprzedniej rekrutacji?"}, {"level": 4, "text": "Czy w rekrutacji na studia pierwszego stopnia  wystarczy mi jedno rozszerzenie?"}, {"level": 4, "text": "Jak wygl\u0105da przepisanie ocen z innego kierunku lub z innej uczelni?"}, {"level": 4, "text": "Czy aplikacja mObywatel jest potrzebna do rekrutacji na AGH?"}, {"level": 4, "text": "Przy wpisie na list\u0119 student\u00f3w I roku otrzyma\u0142em skierowanie na badania lekarskie\u2026"}, {"level": 4, "text": "Posiadam wykszta\u0142cenie uzyskane za granic\u0105. Jak wygl\u0105da procedura rekrutacji? Jakich formalno\u015bci musz\u0119 dope\u0142ni\u0107?"}, {"level": 4, "text": "Jak liczymy nasz wska\u017anik rekrutacyjny? (studia I stopnia)"}, {"level": 4, "text": "Poprawia\u0142em matur\u0119 i otrzyma\u0142em aneks z nowymi wynikami. Jakie dane mam wpisa\u0107 w systemie rekrutacyjnym?"}, {"level": 4, "text": "Kiedy uzyskam informacj\u0119 o warto\u015bci mojego wska\u017anika rekrutacji?"}, {"level": 4, "text": "Posiadam podw\u00f3jne obywatelstwo. Na jakich zasadach b\u0119d\u0119 rekrutowany?"}, {"level": 4, "text": "Czemu nie mog\u0119 si\u0119 zalogowa\u0107 na konto z poprzedniej rekrutacji?"}, {"level": 4, "text": "Jak wygl\u0105da przepisanie ocen z innego kierunku lub z innej uczelni?"}, {"level": 4, "text": "Czy aplikacja mObywatel jest potrzebna do rekrutacji na AGH?"}, {"level": 4, "text": "Przy wpisie na list\u0119 student\u00f3w I roku otrzyma\u0142em skierowanie na badania lekarskie\u2026"}, {"level": 4, "text": "Posiadam wykszta\u0142cenie uzyskane za granic\u0105. Jak wygl\u0105da procedura rekrutacji? Jakich formalno\u015bci musz\u0119 dope\u0142ni\u0107?"}, {"level": 4, "text": "Nie zosta\u0142em zakwalifikowany na studia drugiego stopnia w pierwszym cyklu rekrutacyjnym. Czy mog\u0119 wzi\u0105\u0107 udzia\u0142 w drugim cyklu na ten sam kierunek, co w pierwszym?"}, {"level": 4, "text": "Czy mog\u0119 dokona\u0107 wpisu w terminie innym ni\u017c przewidziany w kalendarzu rekrutacji dla danego cyklu?"}, {"level": 4, "text": "Posiadam tytu\u0142 licencjata. Czy mog\u0119 kandydowa\u0107 na dowolny kierunek studi\u00f3w drugiego stopnia?"}, {"level": 4, "text": "Mam zamiar przenie\u015b\u0107 si\u0119 na Akademi\u0119 G\u00f3rniczo-Hutnicz\u0105 z innej uczelni. Jak to zrobi\u0107?"}, {"level": 4, "text": "Kiedy i gdzie sk\u0142ada\u0107 podania o stypendium socjalne? W jaki spos\u00f3b mog\u0119 ubiega\u0107 si\u0119 o przydzia\u0142 miejsca w domu studenckim?"}]}, "content": "# Warunki Rekrutacji \u2013 Strona Centrum Rekrutacji\n\nURL: https://rekrutacja.agh.edu.pl/warunki-rekrutacji/\nCrawled: 2025-03-20 01:07:17\n\nInformacje opracowane na podstawie \nUchwa\u0142y nr 69/2024 Senatu AGH z dnia 19 czerwca 2024 r.\n\u00a0oraz pozosta\u0142ych akt\u00f3w prawnych dost\u0119pnych w zak\u0142adce \nDokumenty\n.\n\nRekrutacja na studia \nstacjonarne\n i \nniestacjonarne\n rozpoczynaj\u0105ce cykl kszta\u0142cenia w roku akademickim 2024/2025 odbywa si\u0119 w tym samym trybie i wg tych samych warunk\u00f3w.\n\nRekrutacja kandydat\u00f3w na pierwszy rok studi\u00f3w przeprowadzana jest w \ncyklach\n rekrutacyjnych.\n\nPodczas rejestracji w systemie e-Rekrutacja, obowi\u0105zkiem kandydata jest potwierdzenie swojej to\u017csamo\u015bci \nprzy u\u017cyciu \naplikacji mObywatel\n (z za\u0142\u0105czonym polskim dowodem osobistym)\n.\n\nKierunki studi\u00f3w pierwszego stopnia rozpoczynaj\u0105ce cykl kszta\u0142cenia w roku akademickim 2024/2025, na kt\u00f3re b\u0119dzie prowadzona rekrutacja zawiera \nUchwa\u0142a 69/2024 Senatu AGH \u2013 Tabela 1\n.\n\nW\u015br\u00f3d deklarowanych przez kandydata kierunk\u00f3w studi\u00f3w nie mo\u017ce znajdowa\u0107 si\u0119 kierunek, na kt\u00f3rym dana osoba aktualnie studiuje lub kt\u00f3ry uko\u0144czy\u0142a na tym samym wydziale AGH w ramach tego samego stopnia studi\u00f3w.\n\nKandydat wst\u0119pnie zakwalifikowany na kilka kierunk\u00f3w studi\u00f3w ostatecznie mo\u017ce dokona\u0107 wpisu tylko na jeden kierunek.\n\nPodstaw\u0105 kwalifikacji\n dla wszystkich kierunk\u00f3w studi\u00f3w pierwszego stopnia w AGH jest \nwska\u017anik rekrutacji WR\n, ustalany wed\u0142ug wzoru:\n\nwz\u00f3r nr 1\n\nWR = M + 3 \u00b7 \nG\n1 \n+ \nG\n2\n\ngdzie\n\nG1 \u2013 \nliczby punkt\u00f3w uzyskanych z\u00a0\nprzedmiotu g\u0142\u00f3wnego \nwymienionego w \nUchwale nr 69/2024 Senatu AGH \u2013 Tabela 1\n w kolumnie \nG\n1\n (w przypadku matematyki uwzgl\u0119dniany jest tylko wynik egzaminu na poziomie rozszerzonym),\n\nG2 \u2013 \nliczby punkt\u00f3w uzyskanych z \nprzedmiotu g\u0142\u00f3wnego\n wymienionego w \nUchwale nr 69/2024 Senatu AGH \u2013 Tabela 1\n w kolumnie \nG\n2\n (w przypadku matematyki uwzgl\u0119dniany jest tylko wynik egzaminu na poziomie rozszerzonym) \nlub kwalifikacji zawodowej wymienionej w \nUchwale nr 69/2024 Senatu AGH\n \u2013 \nTabela 3\n lub \nTabela 4\n)\n.\n\nM\n \u2013 podwojona liczba punkt\u00f3w uzyskanych z \nmatematyki na poziomie podstawowym\n.\n\nTytu\u0142y technika (kwalifikacje zawodowe) uznawane podczas procesu rekrutacji na studia\n \u2014 \nUchwa\u0142a nr 69/2024 Senatu AGH\n \u2013 \nTabela 2\n\nUWAGA: Szczeg\u00f3\u0142owe informacje dotycz\u0105ce sposobu przeliczania punkt\u00f3w dla sk\u0142adnik\u00f3w G1, G2, M dla r\u00f3\u017cnych rodzaj\u00f3w matury zamieszczone s\u0105 poni\u017cej.\n\na) \nEGZAMIN MATURALNY\n \u2013 egzamin przeprowadzany od 2005 roku przez \nCentraln\u0105 Komisj\u0119 Egzaminacyjn\u0105\n dla absolwent\u00f3w szk\u00f3\u0142 ponadpodstawowych w celu uzyskania \u015bwiadectwa dojrza\u0142o\u015bci. Wyniki egzaminu maturalnego s\u0105 wyra\u017cone w skali 0-100%\n\nb) \nEGZAMIN DOJRZA\u0141O\u015aCI\n \u2013 egzamin przeprowadzany do 2005 roku. Wyniki egzaminu dojrza\u0142o\u015bci s\u0105 przedstawione na \u015bwiadectwie dojrza\u0142o\u015bci w skali 2-5 albo 1-6.\n\nc) \nINTERNATIONAL BACCALAUREATE\n (matura mi\u0119dzynarodowa) \u2013 egzamin ko\u0144cz\u0105cy program Diploma Programme. Dyplom matury mi\u0119dzynarodowej International Baccalaureate Diploma wydawany przez organizacj\u0119 International Baccalaureat Organisation w Genewie mo\u017cna uzyska\u0107 jedynie po uko\u0144czeniu szko\u0142y realizuj\u0105cej Diploma Programme. International Baccalaureate Diploma s\u0105 uznawane za r\u00f3wnorz\u0119dne polskiemu \u015bwiadectwu dojrza\u0142o\u015bci bez obowi\u0105zku przeprowadzania nostryfikacji.\n\nd) \nEUROPEAN BACCALAUREATE\n (matura europejska) \u2013 egzamin ko\u0144cz\u0105cy cykl nauczania wy\u0142\u0105cznie w Szko\u0142ach Europejskich lub Szko\u0142ach Europejskich Akredytowanych. Dyplomy European Baccalaureate, wydawane przez Szko\u0142y Europejskie zgodnie z Konwencj\u0105 o statucie Szk\u00f3\u0142 Europejskich s\u0105 uznawane za r\u00f3wnorz\u0119dne polskiemu \u015bwiadectwu dojrza\u0142o\u015bci bez obowi\u0105zku przeprowadzania nostryfikacji.\n\ne) \n\u015aWIADECTWA ZAGRANICZNE\n \u2013 wszystkie \u015bwiadectwa i dyplomy wydane w ramach innych ni\u017c polski systemach o\u015bwiaty, uprawniaj\u0105ce do podj\u0119cia studi\u00f3w wy\u017cszych w kraju ich wydania. \u015awiadectwa i dyplomy uzyskane w systemach o\u015bwiaty pa\u0144stw Unii Europejskiej, Europejskiego Porozumienia o Wolnym Handlu \u2013 Europejskiego Obszaru Gospodarczego oraz Organizacji Wsp\u00f3\u0142pracy Gospodarczej i Rozwoju (OECD) oraz \u015bwiadectwa obj\u0119te umowami mi\u0119dzynarodowymi nie wymagaj\u0105 dokonywania dodatkowych formalno\u015bci i s\u0105 uznawane z mocy prawa. Pozosta\u0142e wymagaj\u0105 decyzji administracyjnej kuratora o\u015bwiaty. \nJe\u017celi posiadasz wykszta\u0142cenie uzyskane w \nzagranicznym systemie o\u015bwiaty\n zapoznaj si\u0119 z informacjami zamieszczonymi \ntutaj\n.\n\nJe\u017celi na \u015bwiadectwie dojrza\u0142o\u015bci kandydat ma wyniki z egzaminu maturalnego z wi\u0119cej ni\u017c jednego przedmiotu g\u0142\u00f3wnego \nG\n1\n i \nG\n2\n (przedmioty g\u0142\u00f3wne wymienione s\u0105 na stronach poszczeg\u00f3lnych \nkierunk\u00f3w\n zgodnie z \nUchwa\u0142\u0105 69/2024 Senatu AGH \u2013 Tabela 1\n), to do wska\u017anika rekrutacyjnego (1) jest wybierany wynik najlepszy, odpowiednio dla element\u00f3w \nG\n1\n i \nG\n2\n wska\u017anika rekrutacji \nWR\n. Ten sam przedmiot nie mo\u017ce by\u0107 uznany w \nG1 i G2\n jednocze\u015bnie.\n\nMaksymalna warto\u015b\u0107 wska\u017anika rekrutacji W wynosi \n1000 pkt\n.\n\nNa pierwszy rok \nstudi\u00f3w stacjonarnych\n pierwszego stopnia w AGH mog\u0105 zosta\u0107 przyj\u0119ci tylko kandydaci, kt\u00f3rzy uzyskali warto\u015b\u0107 wska\u017anika rekrutacji (1) r\u00f3wn\u0105 lub wi\u0119ksz\u0105 ni\u017c \n300 pkt\n.\n\nZ post\u0119powania kwalifikacyjnego w oparciu o wyniki z egzaminu maturalnego zwolnieni s\u0105 laureaci i finali\u015bci olimpiad stopnia centralnego oraz laureaci konkurs\u00f3w og\u00f3lnopolskich, zgodnie z \nUchwa\u0142\u0105 63\n/2024\n Senatu AGH\n w sprawie zasad przyjmowania na studia laureat\u00f3w oraz finalist\u00f3w olimpiad stopnia centralnego, a tak\u017ce laureat\u00f3w konkurs\u00f3w og\u00f3lnopolskich. Laureaci i finali\u015bci olimpiad oraz konkurs\u00f3w mog\u0105 by\u0107 przyj\u0119ci z pomini\u0119ciem post\u0119powania kwalifikacyjnego w oparciu o wyniki z egzaminu maturalnego wy\u0142\u0105cznie \nw roku uzyskania \u015bwiadectwa dojrza\u0142o\u015bci. \nNa stronach \nkierunk\u00f3w\n mo\u017cesz wyszuka\u0107 olimpiady, kt\u00f3re uprawniaj\u0105 do zwolnienia z post\u0119powania kwalifikacyjnego.\n\nWarunkiem skorzystania z mo\u017cliwo\u015bci przyj\u0119cia na pierwszy rok studi\u00f3w pierwszego stopnia lub jednolitych studi\u00f3w magisterskich w AGH z pomini\u0119ciem post\u0119powania kwalifikacyjnego w oparciu o wyniki z egzaminu maturalnego jest \ndokonanie rejestracji\n w systemie e-Rekrutacja i \nprzedstawienie za\u015bwiadczenia\n stwierdzaj\u0105cego uzyskanie tytu\u0142u laureata lub finalisty z danej olimpiady, albo laureata konkursu do dnia zako\u0144czenia rejestracji kandydat\u00f3w na studia w danym cyklu rekrutacyjnym.\n\nPrzeliczenie wska\u017anika rekrutacji nast\u0105pi w systemie e-Rekrutacja po wprowadzeniu przez kandydata ocen oraz po op\u0142aceniu deklaracji.\n\nInformacje opracowane na podstawie \nUchwa\u0142y nr 123/2024 Senatu AGH z dnia 27 listopada 2024 r.\n Zarz\u0105dzenia nr 30/2024 Rektora AGH w Krakowie z dnia 23 maja 2024 r.\n oraz pozosta\u0142ych akt\u00f3w prawnych dost\u0119pnych w zak\u0142adce \nDokumenty\n.\n\nRekrutacja kandydat\u00f3w na pierwszy rok studi\u00f3w obejmuje rejestracj\u0119 kandydat\u00f3w w elektronicznym systemie e-Rekrutacja oraz:\n\n\u2013\n potwierdzenie swojej to\u017csamo\u015bci przy u\u017cyciu \naplikacji mObywatel\n\n\u2013 z\u0142o\u017cenie lub potwierdzenie w systemie e-Rekrutacja przez kandydata deklaracji przyst\u0105pienia do kwalifikacji na dany kierunek studi\u00f3w;\n\n\u2013 udzia\u0142 w egzaminie wst\u0119pnym lub z\u0142o\u017cenie przez kandydata \no\u015bwiadczenia absolwenta AGH w sprawie wyliczenia sk\u0142adnika E wska\u017anika rekrutacji na podstawie wyniku egzaminu kierunkowego\n;\n\n\u2013 wst\u0119pn\u0105 kwalifikacj\u0119 kandydat\u00f3w;\n\n\u2013 z\u0142o\u017cenie przez kandydata podania o przyj\u0119cie na pierwszy rok studi\u00f3w;\n\n\u2013 wpis kandydata na list\u0119 student\u00f3w na dany kierunek pierwszego roku.\n\nPodstaw\u0105 kwalifikacji dla wszystkich kierunk\u00f3w studi\u00f3w drugiego stopnia jest wska\u017anik rekrutacji WR, obliczony wed\u0142ug og\u00f3lnego wzoru:\n\nWR = w\nE\n \u00b7 E + w\nS\n \u00b7 S\n\nw kt\u00f3rym:\n\nE\n \u2013 liczba punkt\u00f3w uzyskanych z przeprowadzonego w AGH egzaminu wst\u0119pnego potwierdzaj\u0105cego osi\u0105gni\u0119cie wybranych kierunkowych efekt\u00f3w kszta\u0142cenia (EKK) w zakresie wiedzy, umiej\u0119tno\u015bci i kompetencji spo\u0142ecznych osi\u0105ganych na pierwszym stopniu danego kierunku studi\u00f3w, o ile jego waga zosta\u0142a okre\u015blona na wy\u017csz\u0105 od 0; egzamin wst\u0119pny oceniany jest w skali 0-100 pkt.,\n\nS\n \u2013 \u015brednia ocen ze studi\u00f3w pierwszego stopnia lub jednolitych studi\u00f3w magisterskich pomno\u017cona przez 20 (gdy w uczelni wydaj\u0105cej dyplom obowi\u0105zuje skala ocen niedostateczny \u2013 bardzo dobry) lub 16,67 (gdy w uczelni wydaj\u0105cej dyplom obowi\u0105zuje skala ocen niedostateczny \u2013 celuj\u0105cy); w przypadku innej skali ocen \u015brednia ocen ze studi\u00f3w jest przeliczana indywidualnie;\n\nw\nE\n \u2013 waga punkt\u00f3w uzyskanych z egzaminu wst\u0119pnego;\n\nw\nS\n \u2013 waga \u015bredniej ocen ze studi\u00f3w pierwszego stopnia lub jednolitych studi\u00f3w magisterskich; wagi w\nE\n i w\nS\n przyjmuj\u0105 warto\u015bci ca\u0142kowite z zakresu od 0 do 10 oraz:\n\nw\nE\n + w\nS\n = 10\n\nWagi sk\u0142adnik\u00f3w wska\u017anika rekrutacji WR dla kierunk\u00f3w drugiego stopnia studi\u00f3w zawarte s\u0105 w \nUchwale Senatu AGH dost\u0119pnej w \nzak\u0142adce \nDokumenty\n oraz na stronach z opisami poszczeg\u00f3lnych kierunk\u00f3w.\n\nKandydat wst\u0119pnie zakwalifikowany na kilka kierunk\u00f3w studi\u00f3w ostatecznie mo\u017ce dokona\u0107 wpisu tylko na jeden kierunek.\n\nW przypadku kandydata legitymuj\u0105cego si\u0119 dokumentem uzyskanym poza granicami Polski r\u00f3wnowa\u017cnym dyplomowi uko\u0144czenia studi\u00f3w wy\u017cszych w Polsce przeliczenia \u015bredniej ocen na skal\u0119 obowi\u0105zuj\u0105c\u0105 w AGH dokonuje Centrum Rekrutacji AGH. \nZapoznaj si\u0119 tak\u017ce z informacjami zamieszczonymi na stronie: \nINFORMACJE DLA KANDYDAT\u00d3W Z ZAGRANICZNYM WYKSZTA\u0141CENIEM \u2013 Studia II stopnia\n.\n\nSzczeg\u00f3\u0142owe warunki rekrutacji na pierwszy rok studi\u00f3w drugiego stopnia\n:\n\n5.1. Wagi sk\u0142adnik\u00f3w wska\u017anika rekrutacji WR dla kierunk\u00f3w drugiego stopnia studi\u00f3w zawarte s\u0105 w \nUchwale Senatu AGH dost\u0119pnej w \nzak\u0142adce \nDokumenty\n\noraz stronach z opisem poszczeg\u00f3lnych kierunk\u00f3w.\n\n5.2. Kierunki studi\u00f3w stacjonarnych i niestacjonarnych drugiego stopnia, na kt\u00f3re b\u0119dzie prowadzona rekrutacja w roku akademickim 2024/2025, okre\u015blone zosta\u0142y w \nUchwale Senatu AGH dost\u0119pnej w \nzak\u0142adce \nDokumenty\n.\n\n5.3 Egzaminy wst\u0119pne obejmowa\u0107 b\u0119d\u0105 sprawdzenie wybranych kierunkowych efekt\u00f3w kszta\u0142cenia (EKK) w zakresie wiedzy, umiej\u0119tno\u015bci i kompetencji spo\u0142ecznych osi\u0105ganych na pierwszym stopniu danego kierunku studi\u00f3w w AGH.\n\n5.4 Dla absolwent\u00f3w AGH, w przypadku kontynuacji studi\u00f3w na tym samym kierunku, podstaw\u0105 wyliczenia warto\u015bci sk\u0142adnika E wska\u017anika rekrutacji mo\u017ce by\u0107 wynik egzaminu kierunkowego sk\u0142adanego na studiach pierwszego stopnia je\u015bli jest przewidziany w szczeg\u00f3\u0142owych zasadach realizacji programu studi\u00f3w ustalonych przez Dziekana Wydzia\u0142u.\n\nWykaz kierunk\u00f3w studi\u00f3w, na kt\u00f3re podstaw\u0105 kwalifikacji mo\u017ce by\u0107 wynik egzaminu kierunkowego jest dost\u0119pny w zak\u0142adce \u201e\nDokumenty\n\u201d (pkt. 3. Egzaminy na II stopie\u0144 studi\u00f3w).\n\n5.5 Zakres egzaminu kierunkowego musi by\u0107 identyczny z zakresem egzaminu wst\u0119pnego na drugi stopie\u0144 studi\u00f3w na tym kierunku.\n\n5.6 Decyzj\u0119 o mo\u017cliwo\u015bci skorzystania z zapis\u00f3w pkt. 5.4 podejmuje Pe\u0142nomocnik Rektora ds. Rekrutacji po zaopiniowaniu przez WZR.\n\n5.7 W przypadku ubiegania si\u0119 o przyj\u0119cie na studia drugiego stopnia ko\u0144cz\u0105ce si\u0119 uzyskaniem tytu\u0142u zawodowego magistra in\u017cyniera kandydat musi posiada\u0107 tytu\u0142 in\u017cyniera, magistra in\u017cyniera lub tytu\u0142 r\u00f3wnowa\u017cny, z zastrze\u017ceniem pkt. 5.8.\n\n5.8 W przypadku niespe\u0142niania warunku okre\u015blonego pkt. 5.7 uzupe\u0142nienie brakuj\u0105cych kompetencji in\u017cynierskich mo\u017cliwe jest w oparciu o czterosemestralny program studi\u00f3w zatwierdzony przez Senat.\n\n5.9 W przypadku niespe\u0142niania warunku okre\u015blonego w pkt. 5.7 i 5.8 oraz posiadania przez kandydata szczeg\u00f3lnych osi\u0105gni\u0119\u0107 uzyskanych w ramach kszta\u0142cenia akademickiego uzupe\u0142nienie brakuj\u0105cych kompetencji in\u017cynierskich mo\u017ce nast\u0105pi\u0107 na zasadach okre\u015blonych w rozstrzygni\u0119ciu Dziekana Wydzia\u0142u odpowiedzialnego za kszta\u0142cenie na danym kierunku studi\u00f3w wydanym na wniosek kandydata.\n\n6.0 W przypadku kierunk\u00f3w studi\u00f3w stacjonarnych drugiego stopnia ko\u0144cz\u0105cych si\u0119 uzyskaniem tytu\u0142u zawodowego magistra in\u017cyniera, dla kt\u00f3rych prowadzona jest rekrutacja w okresie letnim i zimowym:\n\n.\n\u00a0\u00a0 \u00a0 a) na studia trwaj\u0105ce 4 semestry przyjmowani s\u0105 kandydaci posiadaj\u0105cy tytu\u0142 licencjata, magistra lub tytu\u0142 r\u00f3wnowa\u017cny,\n\n.\u00a0\n\u00a0 \u00a0 b) na studia trwaj\u0105ce 3 semestry przyjmowani s\u0105 kandydaci posiadaj\u0105cy tytu\u0142 in\u017cyniera, magistra in\u017cyniera, tytu\u0142 r\u00f3wnorz\u0119dny lub r\u00f3wnowa\u017cny.\n\n6.1 W przypadku ubiegania si\u0119 o przyj\u0119cie na studia drugiego stopnia na kierunek \nIn\u017cynieria Mechatroniczna\n kandydat dodatkowo ponad wymagania okre\u015blone w pkt 1-5 w toku studi\u00f3w pierwszego stopnia musi uzyska\u0107 co najmniej:\n\n.\u00a0\n\u00a0 \u00a0 a) 18 pkt ECTS (European Credit Transfer System) z matematyki oraz\n\n.\n\u00a0\u00a0 \u00a0 b) 12 pkt ECTS z fizyki oraz\n\n.\n\u00a0\u00a0 \u00a0 c) 30 pkt ECTS z innych przedmiot\u00f3w podstawowych z obszaru nauk \u015bcis\u0142ych oraz\n\n.\n\u00a0\u00a0 \u00a0 d) 25 pkt ECTS z przedmiot\u00f3w rozwijaj\u0105cych umiej\u0119tno\u015bci projektowe, w tym przedmiot\u00f3w zako\u0144czonych projektami oraz\n\n.\u00a0\n\u00a0\u00a0\u00a0 e) 2 pkt ECTS z przedmiot\u00f3w nietechnicznych (z grupy przedmiot\u00f3w humanistycznych, ekonomicznych lub spo\u0142ecznych).\n\n6.2 W przypadku ubiegania si\u0119 o przyj\u0119cie na studia drugiego stopnia na kierunek \nRaw Materials Value Chain\n kandydat dodatkowo ponad wymagania okre\u015blone powy\u017cej musi:\n\n.\u00a0\n\u00a0\u00a0\u00a0 a) uko\u0144czy\u0107 studia pierwszego stopnia na kierunku In\u017cynieria G\u00f3rnicza lub In\u017cynieria \u015arodowiska lub In\u017cynieria Mechaniczna,\n\n.\n \u00a0\u00a0\u00a0 b) w przypadku nie spe\u0142nienia warunku okre\u015blonego w pkt 6.2a \u2014 uzyska\u0107 pozytywne rozstrzygni\u0119cie Dziekana okre\u015blaj\u0105ce powinowactwo uko\u0144czonego kierunku studi\u00f3w pierwszego stopnia do co najmniej jednego z kierunk\u00f3w wymienionych w pkt. 6.2a\n\n.\n\u00a0\u00a0\u00a0\u00a0 c) z\u0142o\u017cy\u0107 Curriculum vitae wraz z listem motywacyjnym oraz wniosek o przyj\u0119cie na studia wsp\u00f3lne.\n\n6.3 Spe\u0142nienie dodatkowych warunk\u00f3w, o kt\u00f3rych mowa w pkt. 6.1 i 6.2, weryfikuje Prodziekan ds. Kszta\u0142cenia Wydzia\u0142u prowadz\u0105cego wymieniony tam kierunek. Do wst\u0119pnej kwalifikacji na wy\u017cej wskazany kierunek dopuszczani s\u0105 wy\u0142\u0105cznie kandydaci, kt\u00f3rych weryfikacja zako\u0144czy\u0142a si\u0119 wynikiem pozytywnym. Wynik weryfikacji jest ostateczny i nie podlega zaskar\u017ceniu.\n\n\t\tKierunki studi\u00f3w\t\t\n\nKrok po kroku\n\nKalendarz rekrutacji\n\n\t\t\tWarunki rekrutacji\t\t\n\n\t\t\tKalkulator rekrutacyjny\t\t\n\n\t\t\tDokumenty\t\t\n\n\t\t\tOp\u0142aty\t\t\n\n\t\t\tLiczba miejsc\t\t\n\n\t\t\tKursy Wyr\u00f3wnawcze\t\t\n\n\t\t\t\tUczniowie\t\t\t\n\n\t\t\t\tOlimpijczycy\t\t\t\n\n\t\t\t\tPrymusi AGH\t\t\t\n\n\t\t\t\tSportowcy\t\t\t\n\nZASADY WYLICZANIA WSKA\u0179NIKA REKRUTACJI\n\n\u015awiadectwo dojrza\u0142o\u015bci z wynikami egzaminu maturalnego w skali 0-100% (2005-2024) \n\u015awiadectwo dojrza\u0142o\u015bci z wynikami egzamin dojrza\u0142o\u015bci w skali 1-6 albo 2-5\nEgzamin maturalny/egzamin dojrza\u0142o\u015bci i egzaminy potwierdzaj\u0105ce kwalifikacje w zawodzie (formu\u0142a 2017)\n\nEgzamin maturalny/egzamin dojrza\u0142o\u015bci i egzaminy zawodowe (formu\u0142a 2019)\n1) dla kandydat\u00f3w kwalifikowanych na podstawie wynik\u00f3w egzaminu maturalnego w skali 0-100% punkt\u00f3w, wska\u017anik rekrutacji obliczony jest wed\u0142ug wzoru (1)\n\nwz\u00f3r nr 1\n\nWR = M + 3 \u00b7 \nG\n1 \n+ \nG\n2\n\ngdzie\n\nG\n1\n, \nG\n2\n \u2013 liczby punkt\u00f3w uzyskanych z \nprzedmiotu g\u0142\u00f3wnego\n wymienionego w \nUchwale Senatu 69/2024 \u2013 Tabela 1\n, odpowiednio w kolumnach \nG\n1\n i \nG\n2\n (\nw przypadku matematyki uwzgl\u0119dniany jest tylko wynik egzaminu na poziomie rozszerzonym\n),\n\na) je\u017celi na \u015bwiadectwie dojrza\u0142o\u015bci umieszczony jest wynik z poziomu podstawowego z przedmiot\u00f3w innych ni\u017c matematyka w wysoko\u015bci NP punkt\u00f3w procentowych, to elementy G1, G2 dla poszczeg\u00f3lnych przedmiot\u00f3w wyznaczane s\u0105 wed\u0142ug wzoru (2)\n\nwz\u00f3r nr 2\n\nG\n1,2\n = N\nP\n\nb) je\u017celi na \u015bwiadectwie dojrza\u0142o\u015bci umieszczony jest wynik z egzaminu zdanego na poziomie rozszerzonym w wysoko\u015bci NR punkt\u00f3w procentowych, to elementy G1, G2 dla poszczeg\u00f3lnych przedmiot\u00f3w wyznaczane s\u0105 wed\u0142ug wzoru (3)\n\nwz\u00f3r nr 3\n\n $$\\mathsf{G_{1,2}} = \\left \\{ \\begin{array}{ll} \\mathsf{N_R} &\n\n\\textsf{dla} & \\mathsf{N_R}\\lt \\mathsf{30} \\\\ \\mathsf{N_R+2(N_R-30)} & \\mathsf{dla} & \\mathsf{30} \\leq \\mathsf{N_R} \\leq \\mathsf{80} \\\\ \\mathsf{N_R+100} & \\mathsf{dla} & \\mathsf{N_R} \\gt \\mathsf{80} \\end{array} \\right. $$ \n\nc) w przypadku j\u0119zyka obcego nowo\u017cytnego \u2013 je\u017celi na \u015bwiadectwie dojrza\u0142o\u015bci umieszczony jest wynik z poziomu dwuj\u0119zycznego w wysoko\u015bci ND punkt\u00f3w procentowych to elementy G1, G2 wyznaczane s\u0105 wed\u0142ug wzoru (4)\n\nwz\u00f3r nr 4\n\n $$ \\mathsf{G_{1,2}} = \\left \\{ \\begin{array}{ll} \\mathsf{2*N_D} & \\mathsf{dla} & \\mathsf{N_D}\\lt \\mathsf{30} \\\\ \\mathsf{N_D+100} & \\mathsf{dla} & \\mathsf{30} \\leq \\mathsf{N_D} \\leq \\mathsf{50} \\\\ \\mathsf{200} & \\mathsf{dla} & \\mathsf{N_D} \\gt \\mathsf{50} \\end{array} \\right. $$\n\nW przypadku wyst\u0119powania na \u015bwiadectwie dojrza\u0142o\u015bci r\u00f3wnocze\u015bnie wynik\u00f3w z poziomu podstawowego, rozszerzonego lub dwuj\u0119zycznego z danego przedmiotu do wska\u017anika rekrutacyjnego (1) jest wybierany wynik z poziomu wy\u017cszego.\n\nMaksymalna liczba punkt\u00f3w element\u00f3w G\n1\n, G\n2\n wynosi \n200\n.\n\nSk\u0142adnik M\n\nPodwojona liczba punkt\u00f3w procentowych uzyskanych w cz\u0119\u015bci pisemnej egzaminu maturalnego z matematyki na poziomie podstawowym.\n\nMaksymalna liczba punkt\u00f3w sk\u0142adnika M wynosi \n200\n.\n\n2) dla kandydat\u00f3w kwalifikowanych na podstawie wynik\u00f3w egzaminu dojrza\u0142o\u015bci w skali ocen 1-6 lub 2-5 wska\u017anik rekrutacji obliczony jest zgodnie ze wzorem (1)\n\nwz\u00f3r nr 1\n\nWR = M + 3 \u00b7 \nG\n1 \n+ \nG\n2\n\ngdzie\n\nG\n1\n, G\n2\n\u00a0\u2013 \npodwojona liczba punkt\u00f3w uzyskanych z przeliczenia ocen wed\u0142ug wzoru (6) z cz\u0119\u015bci pisemnej egzaminu dojrza\u0142o\u015bci z przedmiotu g\u0142\u00f3wnego, kt\u00f3rym jest jeden z przedmiot\u00f3w wymienionych w tabeli 1 odpowiednio w kolumnach G\n1\n\u00a0i G\n2\n.\u00a0 \n\nMaksymalna liczba punkt\u00f3w element\u00f3w G\n1\n, G\n2\n wynosi 200.\n\nSk\u0142adnik M\n\nM \u2013 podwojona liczba punkt\u00f3w uzyskanych z przeliczenia wed\u0142ug wzoru (6) oceny z matematyki zdanej w cz\u0119\u015bci ustnej egzaminu dojrza\u0142o\u015bci lub w przypadku, gdy kandydat nie przyst\u0119powa\u0142 do ustnego egzaminu z matematyki, z przeliczenia oceny ko\u0144cowej z matematyki ze \u015bwiadectwa dojrza\u0142o\u015bci albo \u015bwiadectwa uko\u0144czenia szko\u0142y \u015bredniej.\n\nMaksymalna liczba punkt\u00f3w sk\u0142adnika M wynosi 200.\n\nAlgorytm przeliczania ocen na skal\u0119 procentow\u0105 0 \u2013 100% punkt\u00f3w\n\nwz\u00f3r nr 6\n\nN = 30 + 70 (N\n0\n-N\nmin\n)/(N\nmax\n-N\nmin\n)\n\ngdzie:\n\nN \u2013 ocena po przeliczeniu,\n\nN\n0\n \u2013 ocena umieszczona na \u015bwiadectwie dojrza\u0142o\u015bci lub dokumencie r\u00f3wnowa\u017cnym pod warunkiem, \u017ce jest wi\u0119ksza od Nmin,\n\nN\nmin\n \u2013 najni\u017csza ocena pozytywna w skali obowi\u0105zuj\u0105cej w szkole lub instytucji, kt\u00f3ra wyda\u0142a \u015bwiadectwo,\n\nN\nmax\n \u2013 najwy\u017csza ocena pozytywna w skali obowi\u0105zuj\u0105cej w szkole lub instytucji, kt\u00f3ra wyda\u0142a \u015bwiadectwo.\n\nInformacje skierowane do kandydat\u00f3w absolwent\u00f3w technik\u00f3w posiadaj\u0105cych \n\u015bwiadectwo dojrza\u0142o\u015bci i dyplom potwierdzaj\u0105cy kwalifikacje zawodowe w zawodzie nauczanym na poziomie technika\n\n(FORMU\u0141A 2017)\n\nKandydaci ubiegaj\u0105cy si\u0119 o przyj\u0119cie na studia pierwszego stopnia w AGH, kt\u00f3rzy posiadaj\u0105 tytu\u0142 zawodowy technika w zawodach wymienionych w \nUchwale 69/2024 Senatu AGH \u2013 Tabela 2\n\u00a0oraz posiadaj\u0105 dyplom potwierdzaj\u0105cy kwalifikacje w zawodzie mog\u0105 uwzgl\u0119dni\u0107 w sk\u0142adniku G\n2\n wyniki egzamin\u00f3w potwierdzaj\u0105cych kwalifikacje w zawodzie okre\u015blonych w \nUchwale 69/2024 Senatu AGH \u2013 Tabela 4\n.\n\n3) dla kandydat\u00f3w kwalifikowanych na podstawie wynik\u00f3w egzamin\u00f3w maturalnych i egzamin\u00f3w potwierdzaj\u0105cych kwalifikacje w zawodzie, wska\u017anik rekrutacji obliczany jest wed\u0142ug wzoru (1)\n\nwz\u00f3r nr 1\n\nWR = M + 3 \u00b7 \nG\n1 \n+ \nG\n2\n\ngdzie\n\nG\n1\n \u2013 liczba punkt\u00f3w uzyskanych z przeliczenia wyniku z cz\u0119\u015bci pisemnej egzaminu maturalnego albo egzaminu dojrza\u0142o\u015bci z przedmiotu g\u0142\u00f3wnego wymienionego w kolumnie G1 Uchwa\u0142y 93/2023 Senatu AGH \u2013 Tabela 1 (w przypadku matematyki uwzgl\u0119dniany jest tylko wynik egzaminu na poziomie rozszerzonym) wed\u0142ug zasad okre\u015blonych dla \u015bwiadectwa dojrza\u0142o\u015bci z wynikami egzaminu maturalnego w skali 0-100% punkt\u00f3w (pkt 1) albo \u015bwiadectw dojrza\u0142o\u015bci z wynikami egzaminu dojrza\u0142o\u015bci w skali ocen 1-6 lub 2-5 (pkt 2) \u2013 w zale\u017cno\u015bci od posiadanego \u015bwiadectwa.\n\nG\n2\n \u2013 podwojona liczba punkt\u00f3w uzyskanych z przeliczenia wyniku egzaminu potwierdzaj\u0105cego kwalifikacje w zawodzie wymienionego w \nUchwale 69/2024 Senatu AGH w Tabeli 4\n wed\u0142ug poni\u017cszego wzoru:\n\nW = 0,3 x W\np\n + 0,7 x W\npr\n\ngdzie:\n\nW \u2013 wynik egzaminu potwierdzaj\u0105cego kwalifikacje w zawodzie,\n\nW\np\n \u2013 wynik z cz\u0119\u015bci pisemnej egzaminu potwierdzaj\u0105cego kwalifikacje w zawodzie,\n\nW\npr\n \u2013 wynik z cz\u0119\u015bci praktycznej egzaminu potwierdzaj\u0105cego kwalifikacje w zawodzie.\n\nMaksymalna liczba punkt\u00f3w element\u00f3w G1, G2 wynosi 200.\n\nKandydaci mog\u0105 r\u00f3wnie\u017c uwzgl\u0119dni\u0107 w sk\u0142adniku G\n2\n wyniki egzaminu maturalnego z przedmiotu g\u0142\u00f3wnego wymienionego w \nUchwale Senatu 69/2024 \u2013 Tabela 1\n, odpowiednio w kolumnie G\n2\n wed\u0142ug zasad okre\u015blonych dla \u015bwiadectwa dojrza\u0142o\u015bci z wynikami egzaminu maturalnego w skali 0-100% punkt\u00f3w (pkt1) albo \u015bwiadectw dojrza\u0142o\u015bci z wynikami egzaminu dojrza\u0142o\u015bci w skali ocen 1-6 lub 2-5 (pkt2) \u2013 w zale\u017cno\u015bci od posiadanego \u015bwiadectwa.\n\nWa\u017cne informacje!\n\nPosiadasz kwalifikacje zawodowe zdobyte w \nformule 2017\n je\u017celi:\n\nprzyst\u0119powa\u0142e\u015b do \negzamin\u00f3w potwierdzaj\u0105cych kwalifikacje w zawodzie\n;\n\npo zdaniu poszczeg\u00f3lnych egzamin\u00f3w potwierdzaj\u0105cych kwalifikacje w zawodzie otrzyma\u0142e\u015b \n\u015bwiadectwo potwierdzaj\u0105ce kwalifikacj\u0119 w zawodzie\n, na kt\u00f3rych widniej\u0105 dwuliterowe kody kwalifikacji;\n\npo zdaniu egzamin\u00f3w \npotwierdzaj\u0105cych kwalifikacje w zawodzie\n ze wszystkich kwalifikacji wchodz\u0105cych w sk\u0142ad danego zawodu oraz po uzyskaniu wykszta\u0142cenia \u015bredniego otrzyma\u0142e\u015b \ndyplom potwierdzaj\u0105cy kwalifikacje zawodowe\n, na kt\u00f3rym widniej\u0105 oddzielnie wyniki z cz\u0119\u015bci pisemnej i z cz\u0119\u015bci praktycznej uzyskane w ramach wszystkich kwalifikacji wyodr\u0119bnionych w danym zawodzie.\n\nInformacje skierowane do kandydat\u00f3w absolwent\u00f3w technik\u00f3w posiadaj\u0105cych \n\u015bwiadectwo dojrza\u0142o\u015bci i dyplom zawodowy w zawodzie nauczanym na poziomie technika\n\n(FORMU\u0141A 2019)\n\nKandydaci ubiegaj\u0105cy si\u0119 o przyj\u0119cie na studia pierwszego stopnia w AGH, kt\u00f3rzy posiadaj\u0105 tytu\u0142 zawodowy technika w zawodach wymienionych w \nUchwale 69/2024 Senatu AGH \u2013 Tabela 2\n\u00a0oraz posiadaj\u0105 \ndyplom zawodowy\n mog\u0105 uwzgl\u0119dni\u0107 w sk\u0142adniku G\n2\n wyniki \negzamin\u00f3w zawodowych\n okre\u015blonych w \nUchwale 69/2024 Senatu AGH \u2013 Tabela 3\n.\n\n4) dla kandydat\u00f3w kwalifikowanych na podstawie wynik\u00f3w egzamin\u00f3w maturalnych i egzaminu/egzamin\u00f3w zawodowych, wska\u017anik rekrutacji obliczany jest wed\u0142ug wzoru (1)\n\nwz\u00f3r nr 1\n\nWR = M + 3 \u00b7 \nG\n1 \n+ \nG\n2\n\ngdzie\n\nG\n1\n \u2013 liczba punkt\u00f3w uzyskanych z przeliczenia wyniku z cz\u0119\u015bci pisemnej egzaminu maturalnego albo egzaminu dojrza\u0142o\u015bci z przedmiotu g\u0142\u00f3wnego wymienionego w kolumnie G1 \nUchwa\u0142y 69/2024 Senatu AGH \u2013 Tabela 1\n (w przypadku matematyki uwzgl\u0119dniany jest tylko wynik egzaminu na poziomie rozszerzonym) wed\u0142ug zasad okre\u015blonych dla \u015bwiadectwa dojrza\u0142o\u015bci z wynikami egzaminu maturalnego w skali 0-100% punkt\u00f3w (pkt 1) albo \u015bwiadectw dojrza\u0142o\u015bci z wynikami egzaminu dojrza\u0142o\u015bci w skali ocen 1-6 lub 2-5 (pkt 2) \u2013 w zale\u017cno\u015bci od posiadanego \u015bwiadectwa.\n\nG\n2\n \u2013 podwojona liczba punkt\u00f3w uzyskanych z egzaminu zawodowego wymienionego w \nUchwale 69/2024 Senatu AGH w Tabeli 3\n.\n\nMaksymalna liczba punkt\u00f3w element\u00f3w G1, G2 wynosi 200.\n\nKandydaci mog\u0105 r\u00f3wnie\u017c uwzgl\u0119dni\u0107 w sk\u0142adniku G\n2\n wyniki egzaminu maturalnego z przedmiotu g\u0142\u00f3wnego wymienionego w \nUchwale Senatu 69/2024 \u2013 Tabela 1\n, odpowiednio w kolumnie G\n2\n wed\u0142ug zasad okre\u015blonych dla \u015bwiadectwa dojrza\u0142o\u015bci z wynikami egzaminu maturalnego w skali 0-100% punkt\u00f3w (pkt1) albo \u015bwiadectw dojrza\u0142o\u015bci z wynikami egzaminu dojrza\u0142o\u015bci w skali ocen 1-6 lub 2-5 (pkt2) \u2013 w zale\u017cno\u015bci od posiadanego \u015bwiadectwa.\n\nWa\u017cne informacje!\n\nPosiadasz kwalifikacje zawodowe zdobyte w \nformule 2019\n je\u017celi:\n\nprzyst\u0119powa\u0142e\u015b do \negzamin\u00f3w zawodowych\n;\n\npo zdaniu poszczeg\u00f3lnych egzamin\u00f3w zawodowych otrzyma\u0142e\u015b \ncertyfikaty kwalifikacji zawodowej\n, na kt\u00f3rych widniej\u0105 trzyliterowe kody kwalifikacji;\n\npo zdaniu egzamin\u00f3w zawodowych ze wszystkich kwalifikacji wchodz\u0105cych w sk\u0142ad danego zawodu oraz po uzyskaniu wykszta\u0142cenia \u015bredniego otrzyma\u0142e\u015b \ndyplom zawodowy\n, na kt\u00f3rym widnieje \u0142\u0105czny wynik uzyskany w ramach wszystkich kwalifikacji.\n\n\u015awiadectwa zagraniczne\nInternational Baccalaureate (matura mi\u0119dzynarodowa)\n\nEuropean Baccalaureate (matura europejska)\n5) dla kandydat\u00f3w kwalifikowanych na podstawie wynik\u00f3w egzaminu zagranicznego lub wynik\u00f3w kszta\u0142cenia potwierdzonych \u015bwiadectwem, dyplomem lub innym dokumentem, o kt\u00f3rym mowa w art. 69 ust. 2 pkt 4-7 ustawy z dnia 20 lipca 2018 r. Prawo o szkolnictwie wy\u017cszym i nauce z wy\u0142\u0105czeniem matury mi\u0119dzynarodowej (IB) i matury europejskiej (EB) wska\u017anik rekrutacji obliczony jest wed\u0142ug wzoru (1)\n\nwz\u00f3r nr 1\n\nWR = M + 3 \u00b7 \nG\n1 \n+ \nG\n2\n\ngdzie\n\nG\n1\n, G\n2\n \u2013 liczby punkt\u00f3w uzyskanych z przeliczenia ocen z przedmiotu g\u0142\u00f3wnego, kt\u00f3rym jest jeden z przedmiot\u00f3w wymienionych Uchwale 62/2022 Senatu AGH \u2013 Tabela 1 odpowiednio w kolumnach G\n1\n i G\n2\n (w przypadku matematyki uwzgl\u0119dniany jest tylko wynik egzaminu na poziomie rozszerzonym) wed\u0142ug wzor\u00f3w (2), (3) lub (4), w kt\u00f3rych liczby punkt\u00f3w N\nP\n i N\nR\n s\u0105 wynikami przeliczenia oceny ze \u015bwiadectwa na polsk\u0105 skal\u0119 procentow\u0105 zgodnie ze wzorem (6). W przypadku, gdy na dokumencie nie zosta\u0142 okre\u015blony poziom egzaminu jego wynik b\u0119dzie uznany jako r\u00f3wnowa\u017cny poziomowi podstawowemu polskiego egzaminu maturalnego. W krajach, w kt\u00f3rych kandydat mo\u017ce zdawa\u0107 egzamin zewn\u0119trzny, jako dodatkowy egzamin kwalifikacyjny na studia pierwszego stopnia, wynik takiego egzaminu mo\u017ce by\u0107 uznany jako r\u00f3wnowa\u017cny poziomowi rozszerzonemu polskiego egzaminu maturalnego.\n\nMaksymalna liczba punkt\u00f3w element\u00f3w G\n1\n, G\n2\n wynosi 200.\n\na) je\u017celi na \u015bwiadectwie dojrza\u0142o\u015bci umieszczony jest wynik tylko z poziomu podstawowego z przedmiot\u00f3w innych ni\u017c matematyka w wysoko\u015bci N\nP\n punkt\u00f3w procentowych, to elementy G\n1\n, G\n2\n dla poszczeg\u00f3lnych przedmiot\u00f3w wyznaczane s\u0105 wed\u0142ug wzoru\n\nwz\u00f3r nr 2\n\nG\n1,2\n = N\nP\n\nb) je\u017celi na \u015bwiadectwie dojrza\u0142o\u015bci umieszczony jest wynik tylko z poziomu rozszerzonego w wysoko\u015bci N\nR\n punkt\u00f3w procentowych, to elementy G\n1\n, G\n2\n dla poszczeg\u00f3lnych przedmiot\u00f3w wyznaczane s\u0105 wed\u0142ug wzoru (3)\n\nwz\u00f3r nr 3\n\n $$\\mathsf{G_{1,2}} = \\left \\{ \\begin{array}{ll} \\mathsf{N_R} &\n\n\\textsf{dla} & \\mathsf{N_R}\\lt \\mathsf{30} \\\\ \\mathsf{N_R+2(N_R-30)} & \\mathsf{dla} & \\mathsf{30} \\leq \\mathsf{N_R} \\leq \\mathsf{80} \\\\ \\mathsf{N_R+100} & \\mathsf{dla} & \\mathsf{N_R} \\gt \\mathsf{80} \\end{array} \\right. $$ \n\nwz\u00f3r nr 4\n\nN = 30 + 70 (N\n0\n-N\nmin\n)/(N\nmax\n-N\nmin\n)\n\ngdzie:\n\nN \u2013 ocena po przeliczeniu,\n\nN\n0\n \u2013 ocena umieszczona na \u015bwiadectwie dojrza\u0142o\u015bci lub dokumencie r\u00f3wnowa\u017cnym pod warunkiem, \u017ce jest wi\u0119ksza od N\nmin\n,\n\nN\nmin\n \u2013 najni\u017csza ocena pozytywna w skali obowi\u0105zuj\u0105cej w szkole lub instytucji, kt\u00f3ra wyda\u0142a \u015bwiadectwo,\n\nN\nmax\n \u2013 najwy\u017csza ocena pozytywna w skali obowi\u0105zuj\u0105cej w szkole lub instytucji, kt\u00f3ra wyda\u0142a \u015bwiadectwo.\n\nSk\u0142adnik M\n\nM \u2013podwojona liczba punkt\u00f3w uzyskanych z przeliczenia wed\u0142ug wzoru (4) wyniku z cz\u0119\u015bci pisemnej egzaminu z matematyki na poziomie podstawowym.\n\nMaksymalna liczba punkt\u00f3w sk\u0142adnika M wynosi 200.\n\nZapoznaj si\u0119 tak\u017ce z informacjami zamieszonymi na stronie \nINFORMACJE DLA KANDYDAT\u00d3W Z ZAGRANICZNYM WYKSZTA\u0141CENIEM\n.\n\n6) dla kandydat\u00f3w kwalifikowanych na podstawie wynik\u00f3w egzaminu maturalnego zdawanego wed\u0142ug zasad matury mi\u0119dzynarodowej IB (International Baccalaureate) wska\u017anik rekrutacji obliczony jest wed\u0142ug wzoru (1)\n\nwz\u00f3r nr 1\n\nWR = M + 3 \u00b7 \nG\n1 \n+ \nG\n2\n\ngdzie\n\nG\n1\n, G\n2\n \u2013 liczby punkt\u00f3w uzyskanych z przeliczenia wynik\u00f3w z cz\u0119\u015bci pisemnej egzaminu maturalnego z przedmiotu g\u0142\u00f3wnego, kt\u00f3rym jest jeden z przedmiot\u00f3w wymienionych w \nUchwale 69/2024 Senatu AGH \u2013 Tabela 1\n odpowiednio w kolumnach G\n1\n i G\n2\n wed\u0142ug wzor\u00f3w (2), (3) lub (4). W przypadku matematyki uwzgl\u0119dniany jest tylko wynik egzaminu na poziomie HL. Liczby punkt\u00f3w N\nP\n i N\nR\n s\u0105 wynikami przeliczenia oceny ze \u015bwiadectwa matury mi\u0119dzynarodowej na polsk\u0105 skal\u0119 procentow\u0105 zgodnie ze wzorem (6), przy czym N\nP\n liczony jest dla przedmiot\u00f3w zdawanych na poziomie SL, a N\nR\n dla przedmiot\u00f3w zdawanych na poziomie HL.\n\nMaksymalna liczba punkt\u00f3w element\u00f3w G\n1\n, G\n2\n wynosi 200.\n\na) je\u017celi na \u015bwiadectwie dojrza\u0142o\u015bci umieszczony jest wynik tylko z poziomu podstawowego z przedmiot\u00f3w innych ni\u017c matematyka w wysoko\u015bci N\nP\n punkt\u00f3w procentowych, to elementy G\n1\n, G\n2\n dla poszczeg\u00f3lnych przedmiot\u00f3w wyznaczane s\u0105 wed\u0142ug wzoru\n\nwz\u00f3r nr 2\n\nG\n1,2\n = N\nP\n\nb) je\u017celi na \u015bwiadectwie dojrza\u0142o\u015bci umieszczony jest wynik tylko z poziomu rozszerzonego w wysoko\u015bci N\nR\n punkt\u00f3w procentowych, to elementy G\n1\n, G\n2\n dla poszczeg\u00f3lnych przedmiot\u00f3w wyznaczane s\u0105 wed\u0142ug wzoru (3)\n\nwz\u00f3r nr 3\n\n $$\\mathsf{G_{1,2}} = \\left \\{ \\begin{array}{ll} \\mathsf{N_R} &\n\n\\textsf{dla} & \\mathsf{N_R}\\lt \\mathsf{30} \\\\ \\mathsf{N_R+2(N_R-30)} & \\mathsf{dla} & \\mathsf{30} \\leq \\mathsf{N_R} \\leq \\mathsf{80} \\\\ \\mathsf{N_R+100} & \\mathsf{dla} & \\mathsf{N_R} \\gt \\mathsf{80} \\end{array} \\right. $$ \n\nwz\u00f3r nr 4\n\nN = 30 + 70 (N\n0\n-N\nmin\n)/(N\nmax\n-N\nmin\n)\n\ngdzie:\n\nN \u2013 ocena po przeliczeniu,\n\nN\n0\n \u2013 ocena umieszczona na \u015bwiadectwie dojrza\u0142o\u015bci lub dokumencie r\u00f3wnowa\u017cnym pod warunkiem, \u017ce jest wi\u0119ksza od Nmin,\n\nN\nmin\n \u2013 najni\u017csza ocena pozytywna w skali obowi\u0105zuj\u0105cej w szkole lub instytucji, kt\u00f3ra wyda\u0142a \u015bwiadectwo,\n\nN\nmax\n \u2013 najwy\u017csza ocena pozytywna w skali obowi\u0105zuj\u0105cej w szkole lub instytucji, kt\u00f3ra wyda\u0142a \u015bwiadectwo.\n\nSk\u0142adnik M\n\nM \u2013 podwojona liczba punkt\u00f3w uzyskanych z przeliczenia wed\u0142ug wzoru (4) wyniku z cz\u0119\u015bci pisemnej egzaminu maturalnego z matematyki na poziomie SL albo HL w przypadku, gdy kandydat przyst\u0119powa\u0142 do egzaminu z matematyki tylko na poziomie HL.\n\nMaksymalna liczba punkt\u00f3w sk\u0142adnika M wynosi 200.\n\n6) dla \nkandydat\u00f3w\n kwalifikowanych na podstawie wynik\u00f3w egzaminu maturalnego zdawanego wed\u0142ug zasad matury europejskiej EB (European Baccalaureate) wska\u017anik rekrutacji obliczony jest wed\u0142ug wzoru (1)\n\nwz\u00f3r nr 1\n\nWR = M + 3 \u00b7 \nG\n1 \n+ \nG\n2\n\ngdzie\n\nG\n1\n, G\n2\n \u2013 liczby punkt\u00f3w uzyskanych z przeliczenia wynik\u00f3w z cz\u0119\u015bci pisemnej egzaminu maturalnego z przedmiotu g\u0142\u00f3wnego, kt\u00f3rym jest jeden z przedmiot\u00f3w wymienionych w \nUchwale 69/2024 Senatu AGH \u2013 Tabela 1\n odpowiednio w kolumnach G\n1\n i G\n2\n wed\u0142ug wzor\u00f3w (2), (3) lub (4). W przypadku matematyki uwzgl\u0119dniany jest tylko wynik egzaminu na poziomie rozszerzonym (4-5h). Liczby punkt\u00f3w N\nP\n i N\nR\n s\u0105 wynikami przeliczenia oceny ze \u015bwiadectwa matury europejskiej na polsk\u0105 skal\u0119 procentow\u0105 zgodnie ze wzorem (6), przy czym NP liczony jest dla przedmiot\u00f3w zdawanych na poziomie podstawowym (2-3h), a N\nR\n dla przedmiot\u00f3w zdawanych na poziomie rozszerzonym (4-5h).\n\nMaksymalna liczba punkt\u00f3w element\u00f3w G\n1\n, G\n2\n wynosi 200.\n\na) je\u017celi na \u015bwiadectwie dojrza\u0142o\u015bci umieszczony jest wynik tylko z poziomu podstawowego z przedmiot\u00f3w innych ni\u017c matematyka w wysoko\u015bci N\nP\n punkt\u00f3w procentowych, to elementy G\n1\n, G\n2\n dla poszczeg\u00f3lnych przedmiot\u00f3w wyznaczane s\u0105 wed\u0142ug wzoru\n\nwz\u00f3r nr 2\n\nG\n1,2\n = N\nP\n\nb) je\u017celi na \u015bwiadectwie dojrza\u0142o\u015bci umieszczony jest wynik tylko z poziomu rozszerzonego w wysoko\u015bci N\nR\n punkt\u00f3w procentowych, to elementy G\n1\n, G\n2\n dla poszczeg\u00f3lnych przedmiot\u00f3w wyznaczane s\u0105 wed\u0142ug wzoru (3)\n\nwz\u00f3r nr 3\n\n $$\\mathsf{G_{1,2}} = \\left \\{ \\begin{array}{ll} \\mathsf{N_R} &\n\n\\textsf{dla} & \\mathsf{N_R}\\lt \\mathsf{30} \\\\ \\mathsf{N_R+2(N_R-30)} & \\mathsf{dla} & \\mathsf{30} \\leq \\mathsf{N_R} \\leq \\mathsf{80} \\\\ \\mathsf{N_R+100} & \\mathsf{dla} & \\mathsf{N_R} \\gt \\mathsf{80} \\end{array} \\right. $$ \n\nwz\u00f3r nr 4\n\nN = 30 + 70 (N\n0\n-N\nmin\n)/(N\nmax\n-N\nmin\n)\n\ngdzie:\n\nN \u2013 ocena po przeliczeniu,\n\nN\n0\n \u2013 ocena umieszczona na \u015bwiadectwie dojrza\u0142o\u015bci lub dokumencie r\u00f3wnowa\u017cnym pod warunkiem, \u017ce jest wi\u0119ksza od N\nmin\n,\n\nN\nmin\n \u2013 najni\u017csza ocena pozytywna w skali obowi\u0105zuj\u0105cej w szkole lub instytucji, kt\u00f3ra wyda\u0142a \u015bwiadectwo,\n\nN\nmax\n \u2013 najwy\u017csza ocena pozytywna w skali obowi\u0105zuj\u0105cej w szkole lub instytucji, kt\u00f3ra wyda\u0142a \u015bwiadectwo.\n\nSk\u0142adnik M\n\nM \u2013 podwojona liczba punkt\u00f3w uzyskanych z przeliczenia wed\u0142ug wzoru (4) wyniku z cz\u0119\u015bci pisemnej egzaminu maturalnego z matematyki na poziomie podstawowym (2-3h) albo rozszerzonym (4-5h).\n\nMaksymalna liczba punkt\u00f3w sk\u0142adnika M wynosi 200.\n\n\u015awiadectwo dojrza\u0142o\u015bci z wynikami egzaminu maturalnego w skali 0-100% (2005-2024) \n1) dla kandydat\u00f3w kwalifikowanych na podstawie wynik\u00f3w egzaminu maturalnego w skali 0-100% punkt\u00f3w, wska\u017anik rekrutacji obliczony jest wed\u0142ug wzoru (1)\n\nwz\u00f3r nr 1\n\nWR = M + 3 \u00b7 \nG\n1 \n+ \nG\n2\n\ngdzie\n\nG\n1\n, \nG\n2\n \u2013 liczby punkt\u00f3w uzyskanych z \nprzedmiotu g\u0142\u00f3wnego\n wymienionego w \nUchwale Senatu 69/2024 \u2013 Tabela 1\n, odpowiednio w kolumnach \nG\n1\n i \nG\n2\n (\nw przypadku matematyki uwzgl\u0119dniany jest tylko wynik egzaminu na poziomie rozszerzonym\n),\n\na) je\u017celi na \u015bwiadectwie dojrza\u0142o\u015bci umieszczony jest wynik z poziomu podstawowego z przedmiot\u00f3w innych ni\u017c matematyka w wysoko\u015bci NP punkt\u00f3w procentowych, to elementy G1, G2 dla poszczeg\u00f3lnych przedmiot\u00f3w wyznaczane s\u0105 wed\u0142ug wzoru (2)\n\nwz\u00f3r nr 2\n\nG\n1,2\n = N\nP\n\nb) je\u017celi na \u015bwiadectwie dojrza\u0142o\u015bci umieszczony jest wynik z egzaminu zdanego na poziomie rozszerzonym w wysoko\u015bci NR punkt\u00f3w procentowych, to elementy G1, G2 dla poszczeg\u00f3lnych przedmiot\u00f3w wyznaczane s\u0105 wed\u0142ug wzoru (3)\n\nwz\u00f3r nr 3\n\n $$\\mathsf{G_{1,2}} = \\left \\{ \\begin{array}{ll} \\mathsf{N_R} &\n\n\\textsf{dla} & \\mathsf{N_R}\\lt \\mathsf{30} \\\\ \\mathsf{N_R+2(N_R-30)} & \\mathsf{dla} & \\mathsf{30} \\leq \\mathsf{N_R} \\leq \\mathsf{80} \\\\ \\mathsf{N_R+100} & \\mathsf{dla} & \\mathsf{N_R} \\gt \\mathsf{80} \\end{array} \\right. $$ \n\nc) w przypadku j\u0119zyka obcego nowo\u017cytnego \u2013 je\u017celi na \u015bwiadectwie dojrza\u0142o\u015bci umieszczony jest wynik z poziomu dwuj\u0119zycznego w wysoko\u015bci ND punkt\u00f3w procentowych to elementy G1, G2 wyznaczane s\u0105 wed\u0142ug wzoru (4)\n\nwz\u00f3r nr 4\n\n $$ \\mathsf{G_{1,2}} = \\left \\{ \\begin{array}{ll} \\mathsf{2*N_D} & \\mathsf{dla} & \\mathsf{N_D}\\lt \\mathsf{30} \\\\ \\mathsf{N_D+100} & \\mathsf{dla} & \\mathsf{30} \\leq \\mathsf{N_D} \\leq \\mathsf{50} \\\\ \\mathsf{200} & \\mathsf{dla} & \\mathsf{N_D} \\gt \\mathsf{50} \\end{array} \\right. $$\n\nW przypadku wyst\u0119powania na \u015bwiadectwie dojrza\u0142o\u015bci r\u00f3wnocze\u015bnie wynik\u00f3w z poziomu podstawowego, rozszerzonego lub dwuj\u0119zycznego z danego przedmiotu do wska\u017anika rekrutacyjnego (1) jest wybierany wynik z poziomu wy\u017cszego.\n\nMaksymalna liczba punkt\u00f3w element\u00f3w G\n1\n, G\n2\n wynosi \n200\n.\n\nSk\u0142adnik M\n\nPodwojona liczba punkt\u00f3w procentowych uzyskanych w cz\u0119\u015bci pisemnej egzaminu maturalnego z matematyki na poziomie podstawowym.\n\nMaksymalna liczba punkt\u00f3w sk\u0142adnika M wynosi \n200\n.\n\n\u015awiadectwo dojrza\u0142o\u015bci z wynikami egzamin dojrza\u0142o\u015bci w skali 1-6 albo 2-5\n2) dla kandydat\u00f3w kwalifikowanych na podstawie wynik\u00f3w egzaminu dojrza\u0142o\u015bci w skali ocen 1-6 lub 2-5 wska\u017anik rekrutacji obliczony jest zgodnie ze wzorem (1)\n\nwz\u00f3r nr 1\n\nWR = M + 3 \u00b7 \nG\n1 \n+ \nG\n2\n\ngdzie\n\nG\n1\n, G\n2\n\u00a0\u2013 \npodwojona liczba punkt\u00f3w uzyskanych z przeliczenia ocen wed\u0142ug wzoru (6) z cz\u0119\u015bci pisemnej egzaminu dojrza\u0142o\u015bci z przedmiotu g\u0142\u00f3wnego, kt\u00f3rym jest jeden z przedmiot\u00f3w wymienionych w tabeli 1 odpowiednio w kolumnach G\n1\n\u00a0i G\n2\n.\u00a0 \n\nMaksymalna liczba punkt\u00f3w element\u00f3w G\n1\n, G\n2\n wynosi 200.\n\nSk\u0142adnik M\n\nM \u2013 podwojona liczba punkt\u00f3w uzyskanych z przeliczenia wed\u0142ug wzoru (6) oceny z matematyki zdanej w cz\u0119\u015bci ustnej egzaminu dojrza\u0142o\u015bci lub w przypadku, gdy kandydat nie przyst\u0119powa\u0142 do ustnego egzaminu z matematyki, z przeliczenia oceny ko\u0144cowej z matematyki ze \u015bwiadectwa dojrza\u0142o\u015bci albo \u015bwiadectwa uko\u0144czenia szko\u0142y \u015bredniej.\n\nMaksymalna liczba punkt\u00f3w sk\u0142adnika M wynosi 200.\n\nAlgorytm przeliczania ocen na skal\u0119 procentow\u0105 0 \u2013 100% punkt\u00f3w\n\nwz\u00f3r nr 6\n\nN = 30 + 70 (N\n0\n-N\nmin\n)/(N\nmax\n-N\nmin\n)\n\ngdzie:\n\nN \u2013 ocena po przeliczeniu,\n\nN\n0\n \u2013 ocena umieszczona na \u015bwiadectwie dojrza\u0142o\u015bci lub dokumencie r\u00f3wnowa\u017cnym pod warunkiem, \u017ce jest wi\u0119ksza od Nmin,\n\nN\nmin\n \u2013 najni\u017csza ocena pozytywna w skali obowi\u0105zuj\u0105cej w szkole lub instytucji, kt\u00f3ra wyda\u0142a \u015bwiadectwo,\n\nN\nmax\n \u2013 najwy\u017csza ocena pozytywna w skali obowi\u0105zuj\u0105cej w szkole lub instytucji, kt\u00f3ra wyda\u0142a \u015bwiadectwo.\n\nEgzamin maturalny/egzamin dojrza\u0142o\u015bci i egzaminy potwierdzaj\u0105ce kwalifikacje w zawodzie (formu\u0142a 2017)\n\nInformacje skierowane do kandydat\u00f3w absolwent\u00f3w technik\u00f3w posiadaj\u0105cych \n\u015bwiadectwo dojrza\u0142o\u015bci i dyplom potwierdzaj\u0105cy kwalifikacje zawodowe w zawodzie nauczanym na poziomie technika\n\n(FORMU\u0141A 2017)\n\nKandydaci ubiegaj\u0105cy si\u0119 o przyj\u0119cie na studia pierwszego stopnia w AGH, kt\u00f3rzy posiadaj\u0105 tytu\u0142 zawodowy technika w zawodach wymienionych w \nUchwale 69/2024 Senatu AGH \u2013 Tabela 2\n\u00a0oraz posiadaj\u0105 dyplom potwierdzaj\u0105cy kwalifikacje w zawodzie mog\u0105 uwzgl\u0119dni\u0107 w sk\u0142adniku G\n2\n wyniki egzamin\u00f3w potwierdzaj\u0105cych kwalifikacje w zawodzie okre\u015blonych w \nUchwale 69/2024 Senatu AGH \u2013 Tabela 4\n.\n\n3) dla kandydat\u00f3w kwalifikowanych na podstawie wynik\u00f3w egzamin\u00f3w maturalnych i egzamin\u00f3w potwierdzaj\u0105cych kwalifikacje w zawodzie, wska\u017anik rekrutacji obliczany jest wed\u0142ug wzoru (1)\n\nwz\u00f3r nr 1\n\nWR = M + 3 \u00b7 \nG\n1 \n+ \nG\n2\n\ngdzie\n\nG\n1\n \u2013 liczba punkt\u00f3w uzyskanych z przeliczenia wyniku z cz\u0119\u015bci pisemnej egzaminu maturalnego albo egzaminu dojrza\u0142o\u015bci z przedmiotu g\u0142\u00f3wnego wymienionego w kolumnie G1 Uchwa\u0142y 93/2023 Senatu AGH \u2013 Tabela 1 (w przypadku matematyki uwzgl\u0119dniany jest tylko wynik egzaminu na poziomie rozszerzonym) wed\u0142ug zasad okre\u015blonych dla \u015bwiadectwa dojrza\u0142o\u015bci z wynikami egzaminu maturalnego w skali 0-100% punkt\u00f3w (pkt 1) albo \u015bwiadectw dojrza\u0142o\u015bci z wynikami egzaminu dojrza\u0142o\u015bci w skali ocen 1-6 lub 2-5 (pkt 2) \u2013 w zale\u017cno\u015bci od posiadanego \u015bwiadectwa.\n\nG\n2\n \u2013 podwojona liczba punkt\u00f3w uzyskanych z przeliczenia wyniku egzaminu potwierdzaj\u0105cego kwalifikacje w zawodzie wymienionego w \nUchwale 69/2024 Senatu AGH w Tabeli 4\n wed\u0142ug poni\u017cszego wzoru:\n\nW = 0,3 x W\np\n + 0,7 x W\npr\n\ngdzie:\n\nW \u2013 wynik egzaminu potwierdzaj\u0105cego kwalifikacje w zawodzie,\n\nW\np\n \u2013 wynik z cz\u0119\u015bci pisemnej egzaminu potwierdzaj\u0105cego kwalifikacje w zawodzie,\n\nW\npr\n \u2013 wynik z cz\u0119\u015bci praktycznej egzaminu potwierdzaj\u0105cego kwalifikacje w zawodzie.\n\nMaksymalna liczba punkt\u00f3w element\u00f3w G1, G2 wynosi 200.\n\nKandydaci mog\u0105 r\u00f3wnie\u017c uwzgl\u0119dni\u0107 w sk\u0142adniku G\n2\n wyniki egzaminu maturalnego z przedmiotu g\u0142\u00f3wnego wymienionego w \nUchwale Senatu 69/2024 \u2013 Tabela 1\n, odpowiednio w kolumnie G\n2\n wed\u0142ug zasad okre\u015blonych dla \u015bwiadectwa dojrza\u0142o\u015bci z wynikami egzaminu maturalnego w skali 0-100% punkt\u00f3w (pkt1) albo \u015bwiadectw dojrza\u0142o\u015bci z wynikami egzaminu dojrza\u0142o\u015bci w skali ocen 1-6 lub 2-5 (pkt2) \u2013 w zale\u017cno\u015bci od posiadanego \u015bwiadectwa.\n\nWa\u017cne informacje!\n\nPosiadasz kwalifikacje zawodowe zdobyte w \nformule 2017\n je\u017celi:\n\nprzyst\u0119powa\u0142e\u015b do \negzamin\u00f3w potwierdzaj\u0105cych kwalifikacje w zawodzie\n;\n\npo zdaniu poszczeg\u00f3lnych egzamin\u00f3w potwierdzaj\u0105cych kwalifikacje w zawodzie otrzyma\u0142e\u015b \n\u015bwiadectwo potwierdzaj\u0105ce kwalifikacj\u0119 w zawodzie\n, na kt\u00f3rych widniej\u0105 dwuliterowe kody kwalifikacji;\n\npo zdaniu egzamin\u00f3w \npotwierdzaj\u0105cych kwalifikacje w zawodzie\n ze wszystkich kwalifikacji wchodz\u0105cych w sk\u0142ad danego zawodu oraz po uzyskaniu wykszta\u0142cenia \u015bredniego otrzyma\u0142e\u015b \ndyplom potwierdzaj\u0105cy kwalifikacje zawodowe\n, na kt\u00f3rym widniej\u0105 oddzielnie wyniki z cz\u0119\u015bci pisemnej i z cz\u0119\u015bci praktycznej uzyskane w ramach wszystkich kwalifikacji wyodr\u0119bnionych w danym zawodzie.\n\nEgzamin maturalny/egzamin dojrza\u0142o\u015bci i egzaminy zawodowe (formu\u0142a 2019)\nInformacje skierowane do kandydat\u00f3w absolwent\u00f3w technik\u00f3w posiadaj\u0105cych \n\u015bwiadectwo dojrza\u0142o\u015bci i dyplom zawodowy w zawodzie nauczanym na poziomie technika\n\n(FORMU\u0141A 2019)\n\nKandydaci ubiegaj\u0105cy si\u0119 o przyj\u0119cie na studia pierwszego stopnia w AGH, kt\u00f3rzy posiadaj\u0105 tytu\u0142 zawodowy technika w zawodach wymienionych w \nUchwale 69/2024 Senatu AGH \u2013 Tabela 2\n\u00a0oraz posiadaj\u0105 \ndyplom zawodowy\n mog\u0105 uwzgl\u0119dni\u0107 w sk\u0142adniku G\n2\n wyniki \negzamin\u00f3w zawodowych\n okre\u015blonych w \nUchwale 69/2024 Senatu AGH \u2013 Tabela 3\n.\n\n4) dla kandydat\u00f3w kwalifikowanych na podstawie wynik\u00f3w egzamin\u00f3w maturalnych i egzaminu/egzamin\u00f3w zawodowych, wska\u017anik rekrutacji obliczany jest wed\u0142ug wzoru (1)\n\nwz\u00f3r nr 1\n\nWR = M + 3 \u00b7 \nG\n1 \n+ \nG\n2\n\ngdzie\n\nG\n1\n \u2013 liczba punkt\u00f3w uzyskanych z przeliczenia wyniku z cz\u0119\u015bci pisemnej egzaminu maturalnego albo egzaminu dojrza\u0142o\u015bci z przedmiotu g\u0142\u00f3wnego wymienionego w kolumnie G1 \nUchwa\u0142y 69/2024 Senatu AGH \u2013 Tabela 1\n (w przypadku matematyki uwzgl\u0119dniany jest tylko wynik egzaminu na poziomie rozszerzonym) wed\u0142ug zasad okre\u015blonych dla \u015bwiadectwa dojrza\u0142o\u015bci z wynikami egzaminu maturalnego w skali 0-100% punkt\u00f3w (pkt 1) albo \u015bwiadectw dojrza\u0142o\u015bci z wynikami egzaminu dojrza\u0142o\u015bci w skali ocen 1-6 lub 2-5 (pkt 2) \u2013 w zale\u017cno\u015bci od posiadanego \u015bwiadectwa.\n\nG\n2\n \u2013 podwojona liczba punkt\u00f3w uzyskanych z egzaminu zawodowego wymienionego w \nUchwale 69/2024 Senatu AGH w Tabeli 3\n.\n\nMaksymalna liczba punkt\u00f3w element\u00f3w G1, G2 wynosi 200.\n\nKandydaci mog\u0105 r\u00f3wnie\u017c uwzgl\u0119dni\u0107 w sk\u0142adniku G\n2\n wyniki egzaminu maturalnego z przedmiotu g\u0142\u00f3wnego wymienionego w \nUchwale Senatu 69/2024 \u2013 Tabela 1\n, odpowiednio w kolumnie G\n2\n wed\u0142ug zasad okre\u015blonych dla \u015bwiadectwa dojrza\u0142o\u015bci z wynikami egzaminu maturalnego w skali 0-100% punkt\u00f3w (pkt1) albo \u015bwiadectw dojrza\u0142o\u015bci z wynikami egzaminu dojrza\u0142o\u015bci w skali ocen 1-6 lub 2-5 (pkt2) \u2013 w zale\u017cno\u015bci od posiadanego \u015bwiadectwa.\n\nWa\u017cne informacje!\n\nPosiadasz kwalifikacje zawodowe zdobyte w \nformule 2019\n je\u017celi:\n\nprzyst\u0119powa\u0142e\u015b do \negzamin\u00f3w zawodowych\n;\n\npo zdaniu poszczeg\u00f3lnych egzamin\u00f3w zawodowych otrzyma\u0142e\u015b \ncertyfikaty kwalifikacji zawodowej\n, na kt\u00f3rych widniej\u0105 trzyliterowe kody kwalifikacji;\n\npo zdaniu egzamin\u00f3w zawodowych ze wszystkich kwalifikacji wchodz\u0105cych w sk\u0142ad danego zawodu oraz po uzyskaniu wykszta\u0142cenia \u015bredniego otrzyma\u0142e\u015b \ndyplom zawodowy\n, na kt\u00f3rym widnieje \u0142\u0105czny wynik uzyskany w ramach wszystkich kwalifikacji.\n\n\u015awiadectwa zagraniczne\n5) dla kandydat\u00f3w kwalifikowanych na podstawie wynik\u00f3w egzaminu zagranicznego lub wynik\u00f3w kszta\u0142cenia potwierdzonych \u015bwiadectwem, dyplomem lub innym dokumentem, o kt\u00f3rym mowa w art. 69 ust. 2 pkt 4-7 ustawy z dnia 20 lipca 2018 r. Prawo o szkolnictwie wy\u017cszym i nauce z wy\u0142\u0105czeniem matury mi\u0119dzynarodowej (IB) i matury europejskiej (EB) wska\u017anik rekrutacji obliczony jest wed\u0142ug wzoru (1)\n\nwz\u00f3r nr 1\n\nWR = M + 3 \u00b7 \nG\n1 \n+ \nG\n2\n\ngdzie\n\nG\n1\n, G\n2\n \u2013 liczby punkt\u00f3w uzyskanych z przeliczenia ocen z przedmiotu g\u0142\u00f3wnego, kt\u00f3rym jest jeden z przedmiot\u00f3w wymienionych Uchwale 62/2022 Senatu AGH \u2013 Tabela 1 odpowiednio w kolumnach G\n1\n i G\n2\n (w przypadku matematyki uwzgl\u0119dniany jest tylko wynik egzaminu na poziomie rozszerzonym) wed\u0142ug wzor\u00f3w (2), (3) lub (4), w kt\u00f3rych liczby punkt\u00f3w N\nP\n i N\nR\n s\u0105 wynikami przeliczenia oceny ze \u015bwiadectwa na polsk\u0105 skal\u0119 procentow\u0105 zgodnie ze wzorem (6). W przypadku, gdy na dokumencie nie zosta\u0142 okre\u015blony poziom egzaminu jego wynik b\u0119dzie uznany jako r\u00f3wnowa\u017cny poziomowi podstawowemu polskiego egzaminu maturalnego. W krajach, w kt\u00f3rych kandydat mo\u017ce zdawa\u0107 egzamin zewn\u0119trzny, jako dodatkowy egzamin kwalifikacyjny na studia pierwszego stopnia, wynik takiego egzaminu mo\u017ce by\u0107 uznany jako r\u00f3wnowa\u017cny poziomowi rozszerzonemu polskiego egzaminu maturalnego.\n\nMaksymalna liczba punkt\u00f3w element\u00f3w G\n1\n, G\n2\n wynosi 200.\n\na) je\u017celi na \u015bwiadectwie dojrza\u0142o\u015bci umieszczony jest wynik tylko z poziomu podstawowego z przedmiot\u00f3w innych ni\u017c matematyka w wysoko\u015bci N\nP\n punkt\u00f3w procentowych, to elementy G\n1\n, G\n2\n dla poszczeg\u00f3lnych przedmiot\u00f3w wyznaczane s\u0105 wed\u0142ug wzoru\n\nwz\u00f3r nr 2\n\nG\n1,2\n = N\nP\n\nb) je\u017celi na \u015bwiadectwie dojrza\u0142o\u015bci umieszczony jest wynik tylko z poziomu rozszerzonego w wysoko\u015bci N\nR\n punkt\u00f3w procentowych, to elementy G\n1\n, G\n2\n dla poszczeg\u00f3lnych przedmiot\u00f3w wyznaczane s\u0105 wed\u0142ug wzoru (3)\n\nwz\u00f3r nr 3\n\n $$\\mathsf{G_{1,2}} = \\left \\{ \\begin{array}{ll} \\mathsf{N_R} &\n\n\\textsf{dla} & \\mathsf{N_R}\\lt \\mathsf{30} \\\\ \\mathsf{N_R+2(N_R-30)} & \\mathsf{dla} & \\mathsf{30} \\leq \\mathsf{N_R} \\leq \\mathsf{80} \\\\ \\mathsf{N_R+100} & \\mathsf{dla} & \\mathsf{N_R} \\gt \\mathsf{80} \\end{array} \\right. $$ \n\nwz\u00f3r nr 4\n\nN = 30 + 70 (N\n0\n-N\nmin\n)/(N\nmax\n-N\nmin\n)\n\ngdzie:\n\nN \u2013 ocena po przeliczeniu,\n\nN\n0\n \u2013 ocena umieszczona na \u015bwiadectwie dojrza\u0142o\u015bci lub dokumencie r\u00f3wnowa\u017cnym pod warunkiem, \u017ce jest wi\u0119ksza od N\nmin\n,\n\nN\nmin\n \u2013 najni\u017csza ocena pozytywna w skali obowi\u0105zuj\u0105cej w szkole lub instytucji, kt\u00f3ra wyda\u0142a \u015bwiadectwo,\n\nN\nmax\n \u2013 najwy\u017csza ocena pozytywna w skali obowi\u0105zuj\u0105cej w szkole lub instytucji, kt\u00f3ra wyda\u0142a \u015bwiadectwo.\n\nSk\u0142adnik M\n\nM \u2013podwojona liczba punkt\u00f3w uzyskanych z przeliczenia wed\u0142ug wzoru (4) wyniku z cz\u0119\u015bci pisemnej egzaminu z matematyki na poziomie podstawowym.\n\nMaksymalna liczba punkt\u00f3w sk\u0142adnika M wynosi 200.\n\nZapoznaj si\u0119 tak\u017ce z informacjami zamieszonymi na stronie \nINFORMACJE DLA KANDYDAT\u00d3W Z ZAGRANICZNYM WYKSZTA\u0141CENIEM\n.\n\nInternational Baccalaureate (matura mi\u0119dzynarodowa)\n\n6) dla kandydat\u00f3w kwalifikowanych na podstawie wynik\u00f3w egzaminu maturalnego zdawanego wed\u0142ug zasad matury mi\u0119dzynarodowej IB (International Baccalaureate) wska\u017anik rekrutacji obliczony jest wed\u0142ug wzoru (1)\n\nwz\u00f3r nr 1\n\nWR = M + 3 \u00b7 \nG\n1 \n+ \nG\n2\n\ngdzie\n\nG\n1\n, G\n2\n \u2013 liczby punkt\u00f3w uzyskanych z przeliczenia wynik\u00f3w z cz\u0119\u015bci pisemnej egzaminu maturalnego z przedmiotu g\u0142\u00f3wnego, kt\u00f3rym jest jeden z przedmiot\u00f3w wymienionych w \nUchwale 69/2024 Senatu AGH \u2013 Tabela 1\n odpowiednio w kolumnach G\n1\n i G\n2\n wed\u0142ug wzor\u00f3w (2), (3) lub (4). W przypadku matematyki uwzgl\u0119dniany jest tylko wynik egzaminu na poziomie HL. Liczby punkt\u00f3w N\nP\n i N\nR\n s\u0105 wynikami przeliczenia oceny ze \u015bwiadectwa matury mi\u0119dzynarodowej na polsk\u0105 skal\u0119 procentow\u0105 zgodnie ze wzorem (6), przy czym N\nP\n liczony jest dla przedmiot\u00f3w zdawanych na poziomie SL, a N\nR\n dla przedmiot\u00f3w zdawanych na poziomie HL.\n\nMaksymalna liczba punkt\u00f3w element\u00f3w G\n1\n, G\n2\n wynosi 200.\n\na) je\u017celi na \u015bwiadectwie dojrza\u0142o\u015bci umieszczony jest wynik tylko z poziomu podstawowego z przedmiot\u00f3w innych ni\u017c matematyka w wysoko\u015bci N\nP\n punkt\u00f3w procentowych, to elementy G\n1\n, G\n2\n dla poszczeg\u00f3lnych przedmiot\u00f3w wyznaczane s\u0105 wed\u0142ug wzoru\n\nwz\u00f3r nr 2\n\nG\n1,2\n = N\nP\n\nb) je\u017celi na \u015bwiadectwie dojrza\u0142o\u015bci umieszczony jest wynik tylko z poziomu rozszerzonego w wysoko\u015bci N\nR\n punkt\u00f3w procentowych, to elementy G\n1\n, G\n2\n dla poszczeg\u00f3lnych przedmiot\u00f3w wyznaczane s\u0105 wed\u0142ug wzoru (3)\n\nwz\u00f3r nr 3\n\n $$\\mathsf{G_{1,2}} = \\left \\{ \\begin{array}{ll} \\mathsf{N_R} &\n\n\\textsf{dla} & \\mathsf{N_R}\\lt \\mathsf{30} \\\\ \\mathsf{N_R+2(N_R-30)} & \\mathsf{dla} & \\mathsf{30} \\leq \\mathsf{N_R} \\leq \\mathsf{80} \\\\ \\mathsf{N_R+100} & \\mathsf{dla} & \\mathsf{N_R} \\gt \\mathsf{80} \\end{array} \\right. $$ \n\nwz\u00f3r nr 4\n\nN = 30 + 70 (N\n0\n-N\nmin\n)/(N\nmax\n-N\nmin\n)\n\ngdzie:\n\nN \u2013 ocena po przeliczeniu,\n\nN\n0\n \u2013 ocena umieszczona na \u015bwiadectwie dojrza\u0142o\u015bci lub dokumencie r\u00f3wnowa\u017cnym pod warunkiem, \u017ce jest wi\u0119ksza od Nmin,\n\nN\nmin\n \u2013 najni\u017csza ocena pozytywna w skali obowi\u0105zuj\u0105cej w szkole lub instytucji, kt\u00f3ra wyda\u0142a \u015bwiadectwo,\n\nN\nmax\n \u2013 najwy\u017csza ocena pozytywna w skali obowi\u0105zuj\u0105cej w szkole lub instytucji, kt\u00f3ra wyda\u0142a \u015bwiadectwo.\n\nSk\u0142adnik M\n\nM \u2013 podwojona liczba punkt\u00f3w uzyskanych z przeliczenia wed\u0142ug wzoru (4) wyniku z cz\u0119\u015bci pisemnej egzaminu maturalnego z matematyki na poziomie SL albo HL w przypadku, gdy kandydat przyst\u0119powa\u0142 do egzaminu z matematyki tylko na poziomie HL.\n\nMaksymalna liczba punkt\u00f3w sk\u0142adnika M wynosi 200.\n\nEuropean Baccalaureate (matura europejska)\n6) dla \nkandydat\u00f3w\n kwalifikowanych na podstawie wynik\u00f3w egzaminu maturalnego zdawanego wed\u0142ug zasad matury europejskiej EB (European Baccalaureate) wska\u017anik rekrutacji obliczony jest wed\u0142ug wzoru (1)\n\nwz\u00f3r nr 1\n\nWR = M + 3 \u00b7 \nG\n1 \n+ \nG\n2\n\ngdzie\n\nG\n1\n, G\n2\n \u2013 liczby punkt\u00f3w uzyskanych z przeliczenia wynik\u00f3w z cz\u0119\u015bci pisemnej egzaminu maturalnego z przedmiotu g\u0142\u00f3wnego, kt\u00f3rym jest jeden z przedmiot\u00f3w wymienionych w \nUchwale 69/2024 Senatu AGH \u2013 Tabela 1\n odpowiednio w kolumnach G\n1\n i G\n2\n wed\u0142ug wzor\u00f3w (2), (3) lub (4). W przypadku matematyki uwzgl\u0119dniany jest tylko wynik egzaminu na poziomie rozszerzonym (4-5h). Liczby punkt\u00f3w N\nP\n i N\nR\n s\u0105 wynikami przeliczenia oceny ze \u015bwiadectwa matury europejskiej na polsk\u0105 skal\u0119 procentow\u0105 zgodnie ze wzorem (6), przy czym NP liczony jest dla przedmiot\u00f3w zdawanych na poziomie podstawowym (2-3h), a N\nR\n dla przedmiot\u00f3w zdawanych na poziomie rozszerzonym (4-5h).\n\nMaksymalna liczba punkt\u00f3w element\u00f3w G\n1\n, G\n2\n wynosi 200.\n\na) je\u017celi na \u015bwiadectwie dojrza\u0142o\u015bci umieszczony jest wynik tylko z poziomu podstawowego z przedmiot\u00f3w innych ni\u017c matematyka w wysoko\u015bci N\nP\n punkt\u00f3w procentowych, to elementy G\n1\n, G\n2\n dla poszczeg\u00f3lnych przedmiot\u00f3w wyznaczane s\u0105 wed\u0142ug wzoru\n\nwz\u00f3r nr 2\n\nG\n1,2\n = N\nP\n\nb) je\u017celi na \u015bwiadectwie dojrza\u0142o\u015bci umieszczony jest wynik tylko z poziomu rozszerzonego w wysoko\u015bci N\nR\n punkt\u00f3w procentowych, to elementy G\n1\n, G\n2\n dla poszczeg\u00f3lnych przedmiot\u00f3w wyznaczane s\u0105 wed\u0142ug wzoru (3)\n\nwz\u00f3r nr 3\n\n $$\\mathsf{G_{1,2}} = \\left \\{ \\begin{array}{ll} \\mathsf{N_R} &\n\n\\textsf{dla} & \\mathsf{N_R}\\lt \\mathsf{30} \\\\ \\mathsf{N_R+2(N_R-30)} & \\mathsf{dla} & \\mathsf{30} \\leq \\mathsf{N_R} \\leq \\mathsf{80} \\\\ \\mathsf{N_R+100} & \\mathsf{dla} & \\mathsf{N_R} \\gt \\mathsf{80} \\end{array} \\right. $$ \n\nwz\u00f3r nr 4\n\nN = 30 + 70 (N\n0\n-N\nmin\n)/(N\nmax\n-N\nmin\n)\n\ngdzie:\n\nN \u2013 ocena po przeliczeniu,\n\nN\n0\n \u2013 ocena umieszczona na \u015bwiadectwie dojrza\u0142o\u015bci lub dokumencie r\u00f3wnowa\u017cnym pod warunkiem, \u017ce jest wi\u0119ksza od N\nmin\n,\n\nN\nmin\n \u2013 najni\u017csza ocena pozytywna w skali obowi\u0105zuj\u0105cej w szkole lub instytucji, kt\u00f3ra wyda\u0142a \u015bwiadectwo,\n\nN\nmax\n \u2013 najwy\u017csza ocena pozytywna w skali obowi\u0105zuj\u0105cej w szkole lub instytucji, kt\u00f3ra wyda\u0142a \u015bwiadectwo.\n\nSk\u0142adnik M\n\nM \u2013 podwojona liczba punkt\u00f3w uzyskanych z przeliczenia wed\u0142ug wzoru (4) wyniku z cz\u0119\u015bci pisemnej egzaminu maturalnego z matematyki na poziomie podstawowym (2-3h) albo rozszerzonym (4-5h).\n\nMaksymalna liczba punkt\u00f3w sk\u0142adnika M wynosi 200."}