{"content": "#  Partnerzy przemys\u0142owi Wydzia\u0142u -- Wydzia\u0142 In\u017cynierii Materia\u0142owej i Ceramiki AGH \n\nURL: https://ceramika.agh.edu.pl/wspolpraca/partnerzy-przemyslowi-wydzialu\nCrawled: 2025-03-19 21:32:42\n\nPrzejd\u017a do tre\u015bci\n\nPrzejd\u017a do stopki\n\n Partnerzy przemys\u0142owi Wydzia\u0142u \n\nZak\u0142ady P\u0142ytek Ceramicznych \u201eOpoczno\u201d S.A.\n\nZak\u0142ady Porcelany Elektrotechnicznej \u201eZapel\u201d S.A.\n\n\u201ePorcelana \u015al\u0105ska\u201d Sp. z o.o.\n\n\u201eCeramika Parady\u017c\u201d\n\nZak\u0142ad Ceramiki Budowlanej \u201eCeramika Tub\u0105dzin\u201d\n\nKopalnie Surowc\u00f3w Mineralnych \u201eSurmin-Kaolin\u201d S.A.\n\nLhoist Polska Sp. z o.o.\n\nZak\u0142ady Magnezytowe \u201eRopczyce\u201d S.A.\n\nWarta GLASS Group\n\nHuta Szk\u0142a Gospodarczego Tadeusz Wrze\u015bniak, \u0141adna k/Tarnowa\n\nHuta Szk\u0142a \u201ePilkington Polska\u201d Sp.z o.o.\n\nHuta Szk\u0142a Jaros\u0142aw S.A. \u2013 Owens Illinois Polska S.A.\n\nSaint-Gobain Glass Polska Sp. z o. o.\n\nBrass Polska Sp. z o.o.\n\nPrzedsi\u0119biorstwo Wielobran\u017cowe \u201eSolbet\u201d Sp. z o.o.\n\n\u201eATLAS\u201d Wytw\u00f3rnia Klej\u00f3w i Zapraw Budowlanych\n\nPrzedsi\u0119biorstwo Wielobran\u017cowe \u201eCerpol-Koz\u0142owice\u201d Sp. z o.o.\n\nKrotoszy\u0144skie Przedsi\u0119biorstwo Ceramiki Budowlanej CERABUD S.A.\n\nCementownia \u201eO\u017car\u00f3w\u201d S.A.\n\nCementownia \u201eWarta\u201d S.A.\n\nHolcim Polska S.A.\n\nHeidelberg Materials Polska\n\nCEMEX Polska Sp. z o.o.\n\nGeberit Sp. z o.o.\n\nStowarzyszenie Producent\u00f3w Cementu\n\nPrzedsi\u0119biorstwo Produkcji Beton\u00f3w \u201ePrefabet\u201d Sp. z o.o.\n\nSika Poland Sp. z o.o.\n\nTUV Rheinland Polska Sp. z o.o.\n\nSwisspor Polska Sp. z o.o.\n\nZak\u0142ady Porcelany Sto\u0142owej \u201eKarolina\u201d\n\nStrzeblowskie Kopalnie Surowc\u00f3w Mineralnych Sp. z o.o.\n\nHuta Szk\u0142a Walcowanego \u201eJaroszowiec\u201d\n\nZak\u0142ady Porcelany \u201e\u0106miel\u00f3w\u201d Sp. z o.o.\n\nZak\u0142ady Chemiczne \u201ePermedia\u201d S.A.\n\nZak\u0142ady Porcelany w Chodzie\u017cy\n\nFabryka Porcelany \u201eKrzysztof\u201d S.A.\n\nZak\u0142ady Porcelany Sto\u0142owej \u201eLubiana\u201d S.A.\n\nCeramika \u201eAvanti\u201d\n\nZak\u0142ady P\u0142ytek i Wyrob\u00f3w Sanitarnych Jacek Pilch\n\nFabryka Porcelany \u201eWa\u0142brzych\u201d S.A.\n\nArgillon Polska Sp. z o.o.\n\nFabryka Porcelany \u201eKsi\u0105\u017c\u201d Sp. z o.o.\n\nZak\u0142ady Ceramiczne \u201eBoles\u0142awiec\u201d\n\nZak\u0142ady Przemys\u0142u Gipsowego \u201eDolina Nidy\u201d\n\nPrzedsi\u0119biorstwo Zagraniczne POLCOLORIT Sp. z o.o.\n\n\u201eBiegonice-Krak\u00f3w\u201d Sp. z o.o.\n\nPrzedsi\u0119biorstwo Produkcji, Us\u0142ug i Handlu \u201ePREVAR\u201d Sp. z o.o.\n\nPrzedsi\u0119biorstwo Przemys\u0142u Beton\u00f3w \u201ePrefabet-Niegocin\u201d Sp. z o.o.\n\nStro\u0144skie Zak\u0142ady Kamienia Budowlanego \u201eKambud\u201d Sp. z o.o.\n\nPrzedsi\u0119biorstwo Produkcyjno-Handlowo-Us\u0142ugowe \u201eBonarka\u201d Sp. z o.o.\n\n\u201eWIENERBERGER\u201d Ceramika Budowlana\n\nPrzedsi\u0119biorstwo Materia\u0142\u00f3w Ogniotrwa\u0142ych \u201eKOMEX\u201d Sp. z o.o.\n\nPolska Ceramika Ogniotrwa\u0142a \u017bar\u00f3w S.A.\n\nLG. Philips Displays Poland Sp. z o.o.\n\nStowarzyszenie Producent\u00f3w Brukowej Kostki Drogowej\n\nInstytut Mineralnych Materia\u0142\u00f3w Budowlanych, Oddzia\u0142 w Krakowie\n\nPrzedsi\u0119biorstwo Produkcyjno-Us\u0142ugowo-Handlowe \u201eMEDGAL\u201d\n\nTRICOMED S.A.\n\nPrzedsi\u0119biorstwo NEOXE Sp. z o.o.\n\nZak\u0142ad Produkcyjno-Us\u0142ugowo-Handlowy \u201eTELE-KOM\u201d\n\nOTAVI Minerals GmbH\n\nStopka\n\nKana\u0142 WIMiC AGH w serwisie YouTube\nFanpage WIMiC AGH w serwisie Facebook\">\nFanpage AGH w serwisie Linkedin\">\nKana\u0142 AGH w serwisie Twitter\">\nFanpage WIMiC AGH w serwisie Instagram\">\nFanpage AGH w serwisie Tiktok\">\n\n \u00a9 2023 Wydzia\u0142 In\u017cynierii Materia\u0142owej i Ceramiki\n Akademia G\u00f3rniczo-Hutnicza im. Stanis\u0142awa Staszica w Krakowie\n\nBack", "metadata": {"url": "https://ceramika.agh.edu.pl/wspolpraca/partnerzy-przemyslowi-wydzialu", "title": " Partnerzy przemys\u0142owi Wydzia\u0142u -- Wydzia\u0142 In\u017cynierii Materia\u0142owej i Ceramiki AGH ", "depth": 3, "duplicate": false, "content_hash": "e0e11ed4b417d0ac7cf1c2f4a0354c71", "word_count": 362, "headings": [{"level": 1, "text": "Partnerzy przemys\u0142owi Wydzia\u0142u"}, {"level": 2, "text": "Stopka"}]}}