{"content": "# Cennik p\u0142ywalni | Oficjalna strona Basenu AGH\n\nURL: https://www.basen.agh.edu.pl/?page_id=68\nCrawled: 2025-03-19 22:37:54\n\nWybierz zak\u0142adk\u0119:\n\nTermin wa\u017cno\u015bci karnet\u00f3w:\n\n8 wej\u015b\u0107\n\u00a0\u00a0 \u2013 3 miesi\u0105ce\n\n16 wej\u015b\u0107\n \u2013 6 miesi\u0119cy\n\nKarnet umo\u017cliwiaj\u0105cy wej\u015bcie na p\u0142ywalni\u0119 i si\u0142owni\u0119.\n\n\u015awiadczone us\u0142ugi s\u0105 rozliczane zgodnie z obowi\u0105zuj\u0105cymi cennikami.\n\nKarnet wielokrotnego do\u0142adowania. Przy pierwszym zakupie do ceny us\u0142ugi doliczana jest bezzwrotna cena karnetu (15 z\u0142). Karnet wa\u017cny 12 miesi\u0119cy od daty do\u0142adowania.\n\n\u015arodki na karnecie nie podlegaj\u0105 zwrotowi.\n\nRol\u0119 karnetu mo\u017ce pe\u0142ni\u0107 elektroniczna legitymacja studencka posiadaj\u0105ca interfejs zbli\u017ceniowy.\n\nZa pomoc\u0105 karnet\u00f3w op\u0142aca\u0107 mo\u017cna wy\u0142\u0105cznie zaj\u0119cia niezorganizowane- 60 i 90 minutowe.\n\nDodaj komentarz \nAnuluj pisanie odpowiedzi\nMusisz si\u0119 \nzalogowa\u0107\n, aby m\u00f3c doda\u0107 komentarz.", "metadata": {"url": "https://www.basen.agh.edu.pl/?page_id=68", "title": "Cennik p\u0142ywalni | Oficjalna strona Basenu AGH", "depth": 3, "duplicate": false, "content_hash": "cea8ac3d4d965ad5f7a93112393516f1", "word_count": 94, "headings": [{"level": 3, "text": "Dodaj komentarzAnuluj pisanie odpowiedzi"}]}}