{"content": "# Technologie informacyjne \u2013 Historia AGH\n\nURL: https://historia.agh.edu.pl/wiki/Technologie_informacyjne\nCrawled: 2025-03-19 22:01:51\n\nTechnologie informacyjne\n\nZ Historia AGH\n\nReprezentanci:\n\nAndrzej Jan Kos\n, \nN. R. Narayana Murthy\n\n\u0179r\u00f3d\u0142o: \u201e\nhttp://historia.agh.edu.pl/mediawiki/index.php?title=Technologie_informacyjne&oldid=71147\n\u201d\n\nKategoria\n: \nDyscyplina/Specjalno\u015bci", "metadata": {"url": "https://historia.agh.edu.pl/wiki/Technologie_informacyjne", "title": "Technologie informacyjne \u2013 Historia AGH", "depth": 3, "duplicate": false, "content_hash": "18fddccb436f89826d208d404b659316", "word_count": 21, "headings": [{"level": 1, "text": "Technologie informacyjne"}]}}