{"content": "# Pytko Stanis\u0142aw - BaDAP AGH\n\nURL: https://badap.agh.edu.pl/autor/pytko-stanislaw-002621\nCrawled: 2025-03-19 22:34:13\n\nStrona g\u0142\u00f3wna\n/\nLista autor\u00f3w\n/\nPytko Stanis\u0142aw\nPytko Stanis\u0142aw\n, \nprof. dr hab. in\u017c.\n*WIMiR-kkem\n\n*Katedra Konstrukcji i Eksploatacji Maszyn\nWydzia\u0142 In\u017cynierii Mechanicznej i Robotyki\nWsp\u00f3\u0142praca autorska\nKontakt\nE-mail:\n\ns_pytko@agh.edu.pl\nIdentyfikatory autora w systemach zewn\u0119trznych\nProfile autora w systemach zewn\u0119trznych\nOPI Nauka Polska\nHistoria AGH\nPublikacje autora\nFiltruj publikacje wed\u0142ug\nFiltry i wyszukiwanie\nZamknij\nSzukaj\nSzukaj\nWsp\u00f3\u0142autor\nPytko Pawe\u0142\n(\n25\n)\nFurmanik Kazimierz\n(\n19\n)\nBogacz Roman\n(\n4\n)\nKalukiewicz Antoni\n(\n4\n)\nKulinowski Piotr\n(\n4\n)\nWi\u0119cej\n\n53\nJednostka\nWIMiR\n(\n71\n)\nWILiGZ\n(\n3\n)\nWIMiIP\n(\n1\n)\nRok publikacji\n2009\n(\n11\n)\n2010\n(\n10\n)\n2011\n(\n9\n)\n2008\n(\n8\n)\n2002\n(\n7\n)\nWi\u0119cej\n\n12\nTyp publikacji\nfragmenty ksi\u0105\u017cek\n(\n42\n)\nartyku\u0142y\n(\n18\n)\ndokumenty patentowe\n(\n6\n)\nksi\u0105\u017cki\n(\n5\n)\nredakcje czasopism\n(\n1\n)\nCzasopismo\nTribologia\n(\n7\n)\nZagadnienia Eksploatacji Maszyn\n(\n4\n)\nBiuletyn Urz\u0119du Patentowego\n(\n2\n)\nInternational Journal of Ap...\n(\n2\n)\nFizi\u010desk\u00e2 Mezomehanika\n(\n1\n)\nWi\u0119cej\n\n8\nS\u0142owa kluczowe\nbelt conveyors\n(\n3\n)\nprzeno\u015bniki ta\u015bmowe\n(\n3\n)\nfriction\n(\n2\n)\nkr\u0105\u017cnik centruj\u0105cy\n(\n2\n)\ntarcie\n(\n2\n)\nWi\u0119cej\n\n23\nPunktacja ministerialna\nNie\n(\n45\n)\nTak\n(\n27\n)\nIF/LF\nNie\n(\n18\n)\nBazy referencyjne\nBazTech\n(\n6\n)\nRecenzowane\nNie\n(\n40\n)\nTak\n(\n32\n)\nNaukowe\nTak\n(\n71\n)\nNie\n(\n1\n)\nOtwarty dost\u0119p\nNie\n(\n65\n)\nTak\n(\n7\n)\nJ\u0119zyk publikacji\npolski\n(\n46\n)\nangielski\n(\n12\n)\npubl. wieloj\u0119zyczna\n(\n7\n)\nrosyjski\n(\n7\n)\nNie znaleziono publikacji spe\u0142niaj\u0105cych podane kryteria.", "metadata": {"url": "https://badap.agh.edu.pl/autor/pytko-stanislaw-002621", "title": "Pytko Stanis\u0142aw - BaDAP AGH", "depth": 3, "duplicate": false, "content_hash": "3bc10546e3be4ee452a69ed486f4caf0", "word_count": 279, "headings": [{"level": 1, "text": "Pytko Stanis\u0142aw,prof. dr hab. in\u017c."}, {"level": 2, "text": "*WIMiR-kkem*Katedra Konstrukcji i Eksploatacji Maszyn"}, {"level": 2, "text": "Kontakt"}, {"level": 2, "text": "Identyfikatory autora w systemach zewn\u0119trznych"}, {"level": 2, "text": "Profile autora w systemach zewn\u0119trznych"}, {"level": 2, "text": "Publikacje autora"}, {"level": 3, "text": "Filtruj publikacje wed\u0142ug"}]}}