{"content": "# Kielce \u2013 Historia AGH\n\nURL: https://historia.agh.edu.pl/wiki/Kielce\nCrawled: 2025-03-19 21:57:49\n\nKielce\n\nZ Historia AGH\n\nKielce\n\nMiejsce urodzenia:\n\nData urodzenia\nPelnione funkcje\nRoman G\u00f3recki\n24 stycznia 1936\nJan Stanis\u0142aw Janowski\n20 czerwca 1928\nRektor AGH (1987\u20131993)\nDariusz Knez\n6 grudnia 1969\nWies\u0142aw Madej\n14 czerwca 1944\nJanusz Pra\u017cuch\n13 lipca 1961\nMaciej Tomasz Sitarz\n15 kwietnia 1968\nDanuta Jadwiga \u017bychowicz\n27 lutego 1938\n\nMiejsce \u015bmierci:\n\nData \u015bmierci\nPelnione funkcje\nJerzy Henryk Litwiniszyn\n12 czerwca 2000\nProdziekan Wydzia\u0142u G\u00f3rniczego AGH (1952\u20131954)\n\n\u0179r\u00f3d\u0142o: \u201e\nhttp://historia.agh.edu.pl/mediawiki/index.php?title=Kielce&oldid=27258\n\u201d\n\nKategoria\n: \nMiejscowo\u015b\u0107", "metadata": {"url": "https://historia.agh.edu.pl/wiki/Kielce", "title": "Kielce \u2013 Historia AGH", "depth": 3, "duplicate": false, "content_hash": "2de9ee7280cea552b312269a93716869", "word_count": 76, "headings": [{"level": 1, "text": "Kielce"}]}}