{"content": "# PAOLA \u2013 Academia & Whistleblowing: What\u2019s Next?-- AGH UST \n\nURL: https://agh.edu.pl/en/employees/events/detail/s/final-conference-of-the-paola-project-academia-whistleblowing-whats-next\nCrawled: 2025-03-19 21:22:34\n\nSkip to content\n\nSkip to footer\n\nEvents\n\nEvents\n\n Tags \n\n Search \n\nAI (13)\n\nawards (70)\n\nclimate (4)\n\ncompetitions (36)\n\ncooperation (131)\n\neducation (17)\n\nenvironment (12)\n\ngrants (37)\n\ninnovation (20)\n\nsdg (1)\n\nspace (34)\n\nsports (29)\n\nstudent projects (58)\n\nsupercomputers (4)\n\nPAOLA \u2013 Academia & Whistleblowing: What\u2019s Next?\n\n Download iCal file \n\nAdd to Google Calendar\n\nAdd to Outlook Calendar\n\nAdd to Office 365 Calendar\n\nAdd to Yahoo Calendar\n\n We invite students, doctoral students, and academic staff to attend the Final Conference of the PAOLA Project, held on 20 March 2025 at the AGH University of Krakow, where experts and participants will discuss the future of whistleblowing in academia. \n\n Description \n\nAs part of the \nMarie Curie Annual Conference & General Assembly 2025\n, an EU-supported PAOLA event (The Pandora Box of Whistleblowing in Academia) will take place at the AGH University. This pioneering initiative is dedicated to promoting transparency, integrity, and accountability in academia. Artur Lesner, the AGH University Equality Advocate, has also been invited to join a discussion panel.\n\nWhy attend?\n\nEngage in discussions on academic ethics and best practices\n\nConnect with leading experts, researchers, and fellow students\n\nBe part of a movement shaping a more ethical research environment\n\n\ud83d\udccc \nRegister now\n \u2013 the number of places is limited!\n\nLet\u2019s work together for a more transparent and responsible academia!\n\nOther news from this category\n\n Idea Warm Up \u2013 join and take action!\t\n\n Ambassador of Vietnam visits AGH University\t\n\n Winners of IT is ME Student Innovation Competition\t\n\n AGH University dominates Polish Academic Championship in snowboarding\t\n\n AGH University scientists in the Council for Women in Higher Education and Science\t\n\nRecent news\n\n Idea Warm Up \u2013 join and take action!\t\n\n Ambassador of Vietnam visits AGH University\t\n\n Winners of IT is ME Student Innovation Competition\t\n\n Recruitment for Erasmus+ KA171 \u2013 Third Countries Not Associated to the Programme\t\n\n AGH University dominates Polish Academic Championship in snowboarding\t\n\nStopka\n\nWelcome to AGH University\n\nAGH University Strategy\n\nExcellence Initiative \u2013 Research University\n\nUNIVERSEH\n\nResearch offer\n\nBusiness offer\n\nCentre for International Affairs\n\nWelcome Point\n\nFaculties\n\nMain Library\n\nAGH University Student Campus\n\nCareers Centre\n\nContact\n\nMap of the AGH University Campus\n\nAGH University e-Shop\n\nEmployee Search\n\nHRS4R\n\nEquality statement\n\nPersonal data protection\n\nMake a donation\n\nBack", "metadata": {"url": "https://agh.edu.pl/en/employees/events/detail/s/final-conference-of-the-paola-project-academia-whistleblowing-whats-next", "title": "PAOLA \u2013 Academia & Whistleblowing: What\u2019s Next?-- AGH UST ", "depth": 3, "duplicate": false, "content_hash": "46b7f91cb0f8523e0a224ecf622845e4", "word_count": 364, "headings": [{"level": 1, "text": "Events"}, {"level": 2, "text": "Other news from this category"}, {"level": 2, "text": "Recent news"}, {"level": 2, "text": "Stopka"}]}}