{"content": "# Recruitment for the Erasmus + program for the 2025/2026 academic year has begun-- AGH University Doctoral School \n\nURL: https://www.sd.agh.edu.pl/en/news/detail?tx_news_pi1%5Baction%5D=detail&tx_news_pi1%5Bcontroller%5D=News&tx_news_pi1%5Bnews%5D=1217&cHash=8db2d0773cade0fddaa147c619b1aee2\nCrawled: 2025-03-19 21:21:57\n\nRecruitment for the Erasmus + program for the 2025/2026 academic year has begun \n\n 17-03-2025 \n\n Submission of application documents for study trips continues until April 11, 2025. \n\nDetailed information is available on the \nERASMUS+\n website.\n\nBack", "metadata": {"url": "https://www.sd.agh.edu.pl/en/news/detail?tx_news_pi1%5Baction%5D=detail&tx_news_pi1%5Bcontroller%5D=News&tx_news_pi1%5Bnews%5D=1217&cHash=8db2d0773cade0fddaa147c619b1aee2", "title": "Recruitment for the Erasmus + program for the 2025/2026 academic year has begun-- AGH University Doctoral School ", "depth": 3, "duplicate": false, "content_hash": "fcf2d0c9b91f47d85e5e832229c055df", "word_count": 35, "headings": [{"level": 1, "text": "Recruitment for the Erasmus + program for the 2025/2026 academic year has begun"}, {"level": 1, "text": "Detailed information is available on theERASMUS+website."}, {"level": 2, "text": "Stopka"}]}}