{"content": "# Tekst \u017ar\u00f3d\u0142owy strony Sigward Arne Eklund \u2013 Historia AGH\n\nURL: https://historia.agh.edu.pl/mediawiki/index.php?title=Sigward_Arne_Eklund&action=edit\nCrawled: 2025-03-19 22:19:28\n\nTekst \u017ar\u00f3d\u0142owy strony Sigward Arne Eklund\n\n\u2190 \nSigward Arne Eklund\n\nNie masz uprawnie\u0144 do edytowania tej strony z nast\u0119puj\u0105cego powodu:\n\nWykonywanie tej operacji zosta\u0142o ograniczone do u\u017cytkownik\u00f3w w grupie \nU\u017cytkownicy\n.\n\nTekst \u017ar\u00f3d\u0142owy strony mo\u017cna podejrze\u0107 i skopiowa\u0107.\n\n{{Infobox scientist\n|family-name=Eklund\n|given-name=Sigward Arne\n|honorific-prefix=Dr\n|image=Sigward_Eklund.jpg\n|birth_date=19 czerwca 1911\n|birth_place=Kiruna\n|death_date=30 stycznia 2000\n|death_place=Wiede\u0144\n|fields=energia j\u0105drowa\n|dhc_year=1971\n|dhc_reason=za zas\u0142ugi dla pokojowego wykorzystania energii j\u0105drowej w\u00a0skali \u015bwiatowej i\u00a0rozw\u00f3j szerokiej wsp\u00f3\u0142pracy mi\u0119dzynarodowej w\u00a0tej dziedzinie\n|honorAGH=Doktor Honoris Causa AGH\n|name=Sigward Arne Eklund\n|image_size=11329\n}}\nDr '''Sigward Arne Eklund''' (1911-2000)\n\nDyscyplina/specjalno\u015bci: energia j\u0105drowa\n\n== Nota biograficzna == \nUrodzi\u0142 si\u0119 19 czerwca 1911 roku w\u00a0miejscowo\u015bci Kiruna w\u00a0Szwecji. Zmar\u0142 w Wiedniu 30 stycznia 2000 roku.\n\nUko\u0144czy\u0142 studia w\u00a0uniwersytecie w\u00a0Uppsala. W\u00a0latach 1937\u20131945 pracowa\u0142 w\u00a0Nobel Institute for Physics, w\u00a01946\u00a0roku by\u0142 asystentem Royal Institute of Technology w\u00a0Sztokholmie. W\u00a0latach 1946\u20131950 pracownik Research Institute for National Defence Stockholm.\n\nW\u00a0latach 1950\u20131956 dyrektor Research AB Atomenergi w\u00a0Sztokholmie, w 1957 Sekretarz Generalny Drugiej Mi\u0119dzynarodowej Konferencji Narod\u00f3w Zjednoczonych w sprawie pokojowego wykorzystania energii atomowej, od 1961 do 1981 roku przez cztery kadencje (1965, 1969, 1974, 1977) pe\u0142ni\u0142 funkcj\u0119 dyrektora generalnego Mi\u0119dzynarodowej Agencji Energii Atomowej (IAEA) w\u00a0Wiedniu, od 1981\u00a0roku emerytowany dyrektor generalny.\n\nJego najwi\u0119ksze dokonania jako dyrektora generalnego Mi\u0119dzynarodowej Agencji Energii Atomowej w Wiedniu to zawarcie umowy z laboratoriami IAEA w Monako, w celu poszerzenia zakresu bada\u0144 dotycz\u0105cych skutk\u00f3w radioaktywno\u015bci na \u017cycie w morzu oraz rozbudowa laboratori\u00f3w IAEA w Seibersdorf (Austria).\n\nCz\u0142onek Kr\u00f3lewskiej Szwedzkiej Akademii Nauk od 1972\u00a0roku, Fellow, American Nuclear Society (1961), honorowy cz\u0142onek British Nuclear Engineering Society (1963), American Nuclear Society (1992) i\u00a0inne.\n\nLiczne doktoraty honoris causa: Graz (1968), Bukareszt (1971), Chalmers Institute of Technology, Gothenburg, Szwecja (1974), Moscow State University (1977), uniwersytety: Columbia (1977), Buenos Aires (1977), Drezno (1978), Seul (1978), Peru (1979).\n\n==== Odznaczenia i nagrody ==== \nAtoms for Peace (1968), Grand Cordon Order of the Sacred Treasure (Japonia 1991), Gold Medal, Province of Vienna (1971), Swedish Energy Prize (1991)\n\n== \u0179r\u00f3d\u0142a do biogramu ==\n==== Ksi\u0105\u017cki ==== \n* 75 lat Akademii G\u00f3rniczo-Hutniczej im. Stanis\u0142awa Staszica w Krakowie. Krak\u00f3w 1994, [rozdz.:] Doktorzy honoris causa AGH, s. [6], [foto]\n* The International Who's Who 2000. London 1999, s. 448\n\n==== Artyku\u0142y ==== \n* Wykaz os\u00f3b, kt\u00f3re otrzyma\u0142y Doktoraty Honoris Causa Akademii G\u00f3rniczo-Hutniczej. ''Biuletyn Informacyjny Pracownik\u00f3w AGH'' 1994, nr 5, s. 18\n\n==== Inne ==== \n* [Dyplom nadania DHC AGH] (materia\u0142y Archiwum AGH)\n* In Memoriam: Dr. Sigvard Eklund... [online] [przegl\u0105dany 16.11.2016]. Dost\u0119pny w: https://www.iaea.org/about/dg/eklund/memoriam \n* Na podstawie materia\u0142\u00f3w Muzeum Historii AGH \n* Sigvard Eklund [online] [przegl\u0105dany 16.11.2016]. Dost\u0119pny w: https://en.wikipedia.org/wiki/Sigvard_Eklund \n\n{{DEFAULTSORT:Eklund, Sigward Arne}}\n[[Category:Biogramy]]\n[[Category:Doktorzy honoris causa AGH]]\n\nSzablon u\u017cyty w tym artykule:\n\nSzablon:Infobox scientist\n (\ntekst \u017ar\u00f3d\u0142owy\n) \nWr\u00f3\u0107 do \nSigward Arne Eklund\n.\n\n\u0179r\u00f3d\u0142o: \u201e\nhttp://historia.agh.edu.pl/wiki/Sigward_Arne_Eklund\n\u201d", "metadata": {"url": "https://historia.agh.edu.pl/mediawiki/index.php?title=Sigward_Arne_Eklund&action=edit", "title": "Tekst \u017ar\u00f3d\u0142owy strony Sigward Arne Eklund \u2013 Historia AGH", "depth": 3, "duplicate": false, "content_hash": "c2ac2846ed424c6a25092a0f16e2598c", "word_count": 454, "headings": [{"level": 1, "text": "Tekst \u017ar\u00f3d\u0142owy strony Sigward Arne Eklund"}]}}