{"content": "#  OBSZAR BADAWCZY: Materia\u0142y budowlane -- Wydzia\u0142 In\u017cynierii Materia\u0142owej i Ceramiki AGH \n\nURL: https://ceramika.agh.edu.pl/wspolpraca/oferta-badawcza/mat-budo\nCrawled: 2025-03-19 21:32:43\n\nPrzejd\u017a do tre\u015bci\n\nPrzejd\u017a do stopki\n\n Materia\u0142y budowlane \n\nProjektowanie nowych materia\u0142\u00f3w, rozw\u00f3j nowoczesnych technologii oraz badania w\u0142a\u015bciwo\u015bci materia\u0142\u00f3w budowlanych:\n\nBetony\n\nMateria\u0142y wi\u0105\u017c\u0105ce w tym: cementy, spoiwa wapienne, gipsowe, spoiwa specjalne\n\nNowoczesna ceramika budowlana\n\nMateria\u0142y autoklawizowane\n\nGeopolimery\n\nNowoczesne materia\u0142y izolacyjne\n\n\u201eSmart\u201d materials\n\nKompozyty mineralne\n\nBadania procesu klinkieryzacji i hydratacji spoiw mineralnych\n\nBadania wp\u0142ywu dodatk\u00f3w mineralnych i domieszek chemicznych nowej generacji na proces hydratacji i twardnienia materia\u0142\u00f3w wi\u0105\u017c\u0105cych, beton\u00f3w oraz reologi\u0119 mieszanek ceramicznych, a tak\u017ce na w\u0142a\u015bciwo\u015bci materia\u0142\u00f3w budowlanych\n\nBadania roli materia\u0142\u00f3w budowlanych w gospodarce o cyklu zamkni\u0119tym\n\nMo\u017cliwo\u015bci zastosowania produkt\u00f3w ubocznych w technologii materia\u0142\u00f3w budowlanych\n\nRozw\u00f3j technologii bezklinkierowych materia\u0142\u00f3w wi\u0105\u017c\u0105cych i beton\u00f3w\n\nOcena immobilizacji substancji szkodliwych (w tym metali ci\u0119\u017ckich) w r\u00f3\u017cnego rodzaju spoiwach i betonach\n\nBadania prowadz\u0105ce do obni\u017cenia energoch\u0142onno\u015bci proces\u00f3w produkcyjnych\n\nBadania trwa\u0142o\u015bci materia\u0142\u00f3w budowlanych w r\u00f3\u017cnych warunkach korozyjnych\n\nRozw\u00f3j metod analiz chemicznych stosowanych w technologii materia\u0142\u00f3w budowlanych\n\nZagadnienia zwi\u0105zane z zarz\u0105dzaniem w przemy\u015ble materia\u0142\u00f3w budowlanych.\n\n Ceramika tradycyjna, zaawansowana i materia\u0142y ogniotrwa\u0142e \n\n Szk\u0142o i pow\u0142oki amorficzne \n\n Biomateria\u0142y, kompozyty, polimery i materia\u0142y w\u0119glowe \n\n Chemia analityczna i biochemia \n\n Fizykochemia i modelowanie proces\u00f3w \n\n Chemia nieorganiczna \n\n Chemia krzemian\u00f3w i zwi\u0105zk\u00f3w wielkocz\u0105steczkowych \n\nStopka\n\nKana\u0142 WIMiC AGH w serwisie YouTube\nFanpage WIMiC AGH w serwisie Facebook\">\nFanpage AGH w serwisie Linkedin\">\nKana\u0142 AGH w serwisie Twitter\">\nFanpage WIMiC AGH w serwisie Instagram\">\nFanpage AGH w serwisie Tiktok\">\n\n \u00a9 2023 Wydzia\u0142 In\u017cynierii Materia\u0142owej i Ceramiki\n Akademia G\u00f3rniczo-Hutnicza im. Stanis\u0142awa Staszica w Krakowie\n\nBack", "metadata": {"url": "https://ceramika.agh.edu.pl/wspolpraca/oferta-badawcza/mat-budo", "title": " OBSZAR BADAWCZY: Materia\u0142y budowlane -- Wydzia\u0142 In\u017cynierii Materia\u0142owej i Ceramiki AGH ", "depth": 3, "duplicate": false, "content_hash": "6b9e5ac3bd3294f08c88b5c4da094a5f", "word_count": 227, "headings": [{"level": 1, "text": "Materia\u0142y budowlane"}, {"level": 2, "text": "Stopka"}]}}