{"content": "# Samodzielna Sekcja Eksploatacji Komputer\u00f3w \u2014 SkOs AGH\n\nURL: https://skos.agh.edu.pl/jednostka/akademia-gorniczo-hutnicza-im-stanislawa-staszica-w-krakowie/pion-kwestury/samodzielna-sekcja-eksploatacji-komputerow-132.html\nCrawled: 2025-03-19 21:19:23\n\nPomi\u0144 menu\nPracownicy\nJednostki\nCia\u0142a kolegialne\nZg\u0142oszenie i aktualizacja danych\nInformacje telekomunikacyjne\nSamodzielna Sekcja Eksploatacji Komputer\u00f3w (KW-sek)\nJednostka nadrz\u0119dna\n:\n\nPion Kwestury\nKierownictwo\nkierownik samodzielnej sekcji eksploatacji komputer\u00f3w\nmgr in\u017c.\n\nAndrzej\n\nSzepczy\u0144ski\nOsoba kontaktowa\nmgr in\u017c.\n\nAndrzej\n\nSzepczy\u0144ski\nPok\u00f3j: \nC-1\n\nI p.\n\npok. 106\nTelefony kontaktowe\n +\n\n48\n\n12 617 49 16\nEmail-e kontaktowe\n<!--!Font Awesome Free 6.5.1 by @fontawesome - https://fontawesome.com License - https://fontawesome.com/license/free Copyright 2024 Fonticons, Inc.-->\nProsz\u0119 w\u0142\u0105czy\u0107 JavaScript, aby zobaczy\u0107\nStrony WWW\nhttp://www.kwestura.agh.edu.pl\nOsoby zatrudnione bezpo\u015brednio w jednostce\nHajduk\n\nEwa\n\nMaria\nS\u0142awi\u0144ski\n\nPiotr\n, \nmgr\nSur\u00f3wka\n\nArtur\n, \nmgr\nSzepczy\u0144ski\n\nAndrzej\n, \nmgr in\u017c.\nSzylak\n\nAndrzej\n, \nmgr in\u017c.\nLista os\u00f3b w tej jednostce i jednostkach podrz\u0119dnych", "metadata": {"url": "https://skos.agh.edu.pl/jednostka/akademia-gorniczo-hutnicza-im-stanislawa-staszica-w-krakowie/pion-kwestury/samodzielna-sekcja-eksploatacji-komputerow-132.html", "title": "Samodzielna Sekcja Eksploatacji Komputer\u00f3w \u2014 SkOs AGH", "depth": 3, "duplicate": false, "content_hash": "f7fd2662400a69583f3d5eef8fe0342a", "word_count": 111, "headings": [{"level": 2, "text": "Samodzielna Sekcja Eksploatacji Komputer\u00f3w (KW-sek)"}, {"level": 3, "text": "Jednostka nadrz\u0119dna:"}, {"level": 3, "text": "Kierownictwo"}, {"level": 3, "text": "Osoba kontaktowa"}, {"level": 3, "text": "Telefony kontaktowe"}, {"level": 3, "text": "Email-e kontaktowe"}, {"level": 3, "text": "Strony WWW"}, {"level": 3, "text": "Osoby zatrudnione bezpo\u015brednio w jednostce"}, {"level": 3, "text": "Lista os\u00f3b w tej jednostce i jednostkach podrz\u0119dnych"}]}}